Workbook

Sheet LES MEG
A1: LES MEG — hele modellen forklart i klartekst
A4: HVA MODELLEN GJØR, I ÉN SETNING
A5: Den oversetter resultatmålet ditt (1,5M → 3M → 5M før skatt) til: hvor mange båter som må selges, hvor mange meglere det krever, hva de koster, og hva dere derfor må gjøre hver uke. Charter holdes helt utenfor.
A7: FARGEKODENE
A8: GUL celle med blå skrift = et VALG du kan endre — alt annet regner seg om automatisk.
A9: Svart skrift = utregnet av modellen. Grønn skrift = hentet fra et annet ark. Rød = et gap/avvik du skal styre på.
A11: DE FEM TALLENE SOM STYRER ALT (alle i Forutsetninger)
A12: 1. INNTEKT PER SOLGT BÅT: 58 375 kr ex mva. Målt av oppgjørslistene dine: 4 378 153 kr provisjon delt på 75 solgte båter siste 12 mnd. Vil du ha 1 million mer i omsetning, må dere selge ca. 17 båter mer — eller øke dette tallet (dyrere båter / 6 %-disiplin).
A13: 2. OMSETNING PER MEGLER-STOL: 1,5M per år for en ferdig opplært megler. Tellemåten er KREDITERT omsetning (50/50-splitt når én henter og en annen selger — det lønna følger): Henrik 1,84M, Daniel 0,88M siste 12 mnd. 1,5M er plantallet ditt.
A14: 3. MEGLERKOST: 55 øre av hver megler-krone går til megleren (40 % provisjon + arbeidsgiveravgift + feriepenger). Firmaet beholder 45 øre FØR andre kostnader.
A15: 4. KOSTBASE: 1,88M i året dekker dagens drift (Marte, Philip, kontor, systemer, avskrivning). Vokser dere, vokser den TRINNVIS (fasit-basert fra kostnadsbudsjettet): +60k per megler utover 2 (parkering/lisenser/telefon), +75k engangs per nyansettelse, +900k salgsleder ved 5, +300k kontorutvidelse ved 6 (plassholder — sjekk leieavtalen), +500k backoffice ved 8.
A16: 5. DIN EGEN LØNN: kappet på 7,1G = 969 498 kr — pensjonsopptjeningstaket; over dette lønner utbytte seg. Antas å inkludere feriepenger (12 %) → grunnlønn ≈ 865 623 (Marius bekrefter). Alt du selger utover ca. 2,15M koster ikke firmaet mer lønn — din marginale omsetning er den mest lønnsomme i selskapet.
... A47: Ukentlig drift: Weekly Scorecard (H2-rest-målet: 126 330 kr/uke). Kvartal: kvartalsmålene i Økonomimotor. Året/strategien: resultat-gapet og rekrutteringsgapet i 1-3-5 Plan. Rådgivers vurdering: H2-delen er klar til bruk; 2027–2031 er retningsgivende til trinnkostene er kalibrert og proxyene målt.

Sheet Historikk
A1: HISTORIKK — fasit, kohort og resultatbro
A2: Alt her er MÅLT (oppgjørslister/regnskap/HubSpot) — ingen mål eller antakelser. Charter holdt utenfor båt-tallene.
A4: FASIT SISTE 12 MND (oppgjørslister, 27.08.2025–26.08.2026, ex charter)
A5: Båter solgt | B5: 75
A6: Omsetning ex mva (provisjon) | B6: 4378153 | C6: alle 75 med beløp — fasit, ikke HubSpot
A7: Snitt / median per båt | B7: 58375 | C7: median 50 400
A8: Snitt / median salgssum | B8: 1260458 | C8: median 1 065 000; eff. provisjonsgrad 5,79 % inkl mva
A9: Charter (egen enhet, utenfor motoren) | B9: 170000 | C9: 1 oppdrag (AD Astra)
A11: PER MEGLER — TRE MÅTER Å TELLE (alle fra oppgjørslistene)
A12: OPPDRAG INN = hvem hentet oppdraget · SOLGT AV = hvem lukket salget · KREDITERT = 50/50-splitt ved samarbeid — det lønna følger, og det stol-tallene i modellen bruker.
A13: Megler | B13: Kreditert 12 mnd | C13: Solgt av 12 mnd | D13: Kreditert 2025 | E13: Solgt av 2025 | F13: Oppdrag inn 2025
A14: Henrik (+Marte) | B14: 1838820 | C14: 2007420 | D14: 1599192 | E14: 1962912 | F14: 1156272
A15: Sindre | B15: 1491253 | C15: 1309453 | D15: 2083205 | E15: 1597805 | F15: 2532605
A16: Daniel (slutter) | B16: 882480 | C16: 953280 | D16: 532320 | E16: 570000 | F16: 494640
A17: Jeanette (sluttet) | B17: 165600 | C17: 108000 | D17: 642800 | E17: 726800 | F17: 674000
A18: Sum | B18: =SUM(B14:B17) | C18: =SUM(C14:C17) | D18: =SUM(D14:D17) | E18: =SUM(E14:E17) | F18: =SUM(F14:F17)
A19: Sindre er ANSKAFFELSESMOTOREN (2,5M i oppdrag inn 2025), Henrik er LUKKEMOTOREN (2,0M solgt av) — ~630k av Henriks salg i 2025 var Sindres oppdrag (delt 50/50 i oppgjøret).
A20: RAMP-EMPIRI: Henrik startet mars 2025 → år 1 KREDITERT 1 599 192 (1,9M-rate, delvis ved å lukke Sindres oppdrag). Daniel startet april 2025 → år 1 kreditert 532 320 (0,71M-rate).
A21: → Ramp er PERSONDREVET, ikke tidsdrevet — og kan AKSELERERES ved at Sindre mater nye meglere med oppdrag, slik Henrik fikk i 2025. Snitt år 1-rate ≈ 1,3M kreditert (n=2, enorm spredning); churn-bufferen dekker Daniel-utfallet.
A23: KOHORT: SIGNERT OPPDRAG → SOLGT (HubSpot Pipeline B, 163 oppdrag siden sep 2024)
A24: B-deal opprettet = PROXY for signeringsdato. Closedate delvis bulk-satt (noen umulige salgstider) → indikativt.
A25: Signert kvartal | B25: n | C25: Solgt | D25: Tapt | E25: Åpne | F25: Solgt ≤90 dg | G25: Solgt ≤180 dg | H25: Median dager
A26: 2025-Q1 | B26: 11 | C26: 11 | D26: 0 | E26: 0 | F26: 4 | G26: 8 | H26: 106
A27: 2025-Q2 | B27: 32 | C27: 20 | D27: 8 | E27: 4 | F27: 9 | G27: 16 | H27: 95
A28: 2025-Q3 | B28: 25 | C28: 18 | D28: 0 | E28: 7 | F28: 6 | G28: 9 | H28: 189
A29: 2025-Q4 | B29: 11 | C29: 5 | D29: 5 | E29: 1 | F29: 1 | G29: 4 | H29: 143
A30: 2026-Q1 | B30: 18 | C30: 9 | D30: 1 | E30: 8 | F30: 4 | G30: 9 | H30: 116
A31: 2026-Q2 | B31: 49 | C31: 19 | D31: 2 | E31: 28 | F31: 17 | G31: 19 | H31: 47
A32: 2026-Q3 | B32: 16 | C32: 2 | D32: 0 | E32: 14 | F32: 2 | G32: 2 | H32: (datofeil)
A34: MODNE kohorter (signert >365 dg siden, n=58) | B34: 72 % solgt · 14 % tapt · 14 % fortsatt åpne
A35: → Signerte oppdrag per salg (modne) | B35: 58/42 = 1,38 (hvis alle 8 åpne selges: 58/50 = 1,16)
A36: Salgstid (85 solgte av 163 oppdrag sep-24→nå) | B36: median 89 dg · snitt 123 dg · 51 % ≤90 · 79 % ≤180. NB: annen kilde/periode (HubSpot, 24 mnd) enn fasitens 75 siste 12 mnd
A38: PIPELINE A — OPPDRAG INN (HubSpot, siste 12 mnd per 26.08.2026)
A39: Nye prospects (deals opprettet) | B39: 133
A40: Signert oppdragsavtale (Vunnet) | B40: 67
A41: Tapt | B41: 32
A42: Fortsatt åpne | B42: 34
A43: Vinnrate av avgjorte (67/99) — PROXY | B43: 0.68 | C43: Prospect→befaring per megler (CFO-analyse): Sindre 74 % · Daniel 52 % · Henrik+Marte 28 %
A45: RESULTATBRO 2025 — fra regnskap til modell (avstem «rest» med Marius)
A46: Sum driftsinntekter, årsregnskap 2025 | B46: 6174978 | C46: Endelig årsregnskap, signert 16.06.26
A47: Omsetning oppgjørsbasis ex mva 2025 | B47: 4857517 | C47: Oppgjørslisten 2025
A48: Differanse inntektssiden | B48: =B46-B47 | C48: forklares delvis under:
A49: herav engangs «rydding»-inntekt (3900) | B49: 200000 | C49: ca-beløp
A50: herav Serotonic-gjennomstrømming | B50: 412000 | C50: inntekt m/motsvarende kostnad, netto ~0
A51: herav rest — MÅ AVSTEMMES | B51: =B48-B49-B50 | C51: periodisering 3090, mva-føring, annet — Marius (RVT)
A52: Resultat før skatt 2025, regnskap | B52: 736978 | C52: løftet av underuttak Sindre + engangsposter
A53: Modellert fullastet resultat siste 12 mnd | B53: =Økonomimotor!B28 | C53: negativt: fasit-omsetningen er under dagens break-even

Sheet Økonomimotor
A1: ØKONOMIMOTOR — bemanning → kapasitet → resultat, mot målet
A2: v3: motoren regner nå BEGGE veier. Ned: planlagt bemanning (m/ramp) → kapasitet → P&L → resultat → GAP mot mål.
A3: Referanse nederst: hvilken omsetning målet KREVER (med samme trinnvise kostbase).
B5: Målt siste 12 mnd | C5: År 1 (2027) | D5: År 3 (2029) | E5: År 5 (2031)
A6: INPUT
A7: Resultatmål før skatt [målt = regnskap 2025] | B7: 736978 | C7: 1500000 | D7: 3000000 | E7: 5000000
A8: Sindre-stolens omsetning | B8: 1491253 | C8: =Forutsetninger!$B$14 | D8: =Forutsetninger!$B$14 | E8: =Forutsetninger!$B$14
A9: BEMANNINGSPLAN (PLANANTAKELSE — juster og se resultatet endre seg)
A10: Rampede megler-stoler ved årets start | B10: 1 | C10: 2 | D10: 6 | E10: 9
A11: Nyansettelser Q1 (fra kvartalets start) | B11: 0 | C11: 1 | D11: 1 | E11: 1
A12: Nyansettelser Q2 | B12: 0 | C12: 1 | D12: 1 | E12: 1
A13: Nyansettelser Q3 | B13: 0 | C13: 1 | D13: 0 | E13: 0
A14: Nyansettelser Q4 | B14: 0 | C14: 0 | D14: 0 | E14: 0
A15: EFFEKTIVE producing megler-FTE i året (ramp-vektet) | B15: 1 | C15: =C10+C11*((3*Forutsetninger!$B$20+3*Forutsetninger!$B$21+6*Forutsetninger!$B$22)/12)+C12*((3*Forutsetninger!$B$20+3*Forutsetninger!$B$21+3*Forutsetninger!$B$22)/12)+C13*((3*Forutsetninger!$B$20+3*Forutsetninger!$B$21)/12)+C14*((3*Forutsetninger!$B$20)/12) | D15: =D10+D11*((3*Forutsetninger!$B$20+3*Forutsetninger!$B$21+6*Forutsetninger!$B$22)/12)+D12*((3*Forutsetninger!$B$20+3*Forutsetninger!$B$21+3*Forutsetninger!$B$22)/12)+D13*((3*Forutsetninger!$B$20+3*Forutsetninger!$B$21)/12)+D14*((3*Forutsetninger!$B$20)/12) | E15: =E10+E11*((3*Forutsetninger!$B$20+3*Forutsetninger!$B$21+6*Forutsetninger!$B$22)/12)+E12*((3*Forutsetninger!$B$20+3*Forutsetninger!$B$21+3*Forutsetninger!$B$22)/12)+E13*((3*Forutsetninger!$B$20+3*Forutsetninger!$B$21)/12)+E14*((3*Forutsetninger!$B$20)/12)
A16: MEGLER-STOLER bemannet ved årets slutt | B16: 1 | C16: =C10+SUM(C11:C14) | D16: =D10+SUM(D11:D14) | E16: =E10+SUM(E11:E14)
A17: Gjennomsnittlig bemannede stoler i året (Q1-ansatt teller 100 %, Q2 75 %, Q3 50 %, Q4 25 %) | B17: 1 | C17: =C10+C11*1+C12*0.75+C13*0.5+C14*0.25 | D17: =D10+D11*1+D12*0.75+D13*0.5+D14*0.25 | E17: =E10+E11*1+E12*0.75+E13*0.5+E14*0.25
A18: TRINNVIS KOSTBASE (fasit-basert: 60k/stol + 75k engangs per ansettelse + terskler 5/6/8 på årets slutt)
A19: Kostbase i året, ekskl. markedskost | B19: =Forutsetninger!$B$25+MAX(0,B17-2)*Forutsetninger!$B$26+SUM(B11:B14)*Forutsetninger!$B$27+IF(B16>=5,Forutsetninger!$B$29,0)+IF(B16>=6,Forutsetninger!$B$28,0)+IF(B16>=8,Forutsetninger!$B$30,0) | C19: =Forutsetninger!$B$25+MAX(0,C17-2)*Forutsetninger!$B$26+SUM(C11:C14)*Forutsetninger!$B$27+IF(C16>=5,Forutsetninger!$B$29,0)+IF(C16>=6,Forutsetninger!$B$28,0)+IF(C16>=8,Forutsetninger!$B$30,0) | D19: =Forutsetninger!$B$25+MAX(0,D17-2)*Forutsetninger!$B$26+SUM(D11:D14)*Forutsetninger!$B$27+IF(D16>=5,Forutsetninger!$B$29,0)+IF(D16>=6,Forutsetninger!$B$28,0)+IF(D16>=8,Forutsetninger!$B$30,0) | E19: =Forutsetninger!$B$25+MAX(0,E17-2)*Forutsetninger!$B$26+SUM(E11:E14)*Forutsetninger!$B$27+IF(E16>=5,Forutsetninger!$B$29,0)+IF(E16>=6,Forutsetninger!$B$28,0)+IF(E16>=8,Forutsetninger!$B$30,0)
A20: KAPASITET → RESULTAT (P&L på planlagt bemanning)
A21: Kapasitets-omsetning ex mva (FTE × stol + Sindre) | B21: 4378153 | C21: =C15*Forutsetninger!$B$13+C8 | D21: =D15*Forutsetninger!$B$13+D8 | E21: =E15*Forutsetninger!$B$13+E8
A22: Båter solgt (omsetning ÷ inntekt per båt) | B22: 75 | C22: =C21/Forutsetninger!$B$5 | D22: =D21/Forutsetninger!$B$5 | E22: =E21/Forutsetninger!$B$5
A23: Signerte oppdrag inn (båter × 1,30 — planantakelse) | B23: 67 | C23: =C22*Forutsetninger!$B$41 | D23: =D22*Forutsetninger!$B$41 | E23: =E22*Forutsetninger!$B$41
A24: − Meglerkost inkl. AGA/feriepenger (55 % av megler-oms) | B24: =-Forutsetninger!$B$34*(B21-B8) | C24: =-Forutsetninger!$B$34*(C21-C8) | D24: =-Forutsetninger!$B$34*(D21-D8) | E24: =-Forutsetninger!$B$34*(E21-E8)
A25: − Sindre-kompensasjon (min av 45 % og 7,1G, loaded) | B25: =-MIN(Forutsetninger!$B$37*B8,Forutsetninger!$B$36)*Forutsetninger!$B$38 | C25: =-MIN(Forutsetninger!$B$37*C8,Forutsetninger!$B$36)*Forutsetninger!$B$38 | D25: =-MIN(Forutsetninger!$B$37*D8,Forutsetninger!$B$36)*Forutsetninger!$B$38 | E25: =-MIN(Forutsetninger!$B$37*E8,Forutsetninger!$B$36)*Forutsetninger!$B$38
A26: − Markedskost (per signert oppdrag × oppdrag inn) | B26: =-Forutsetninger!$B$31*B23 | C26: =-Forutsetninger!$B$31*C23 | D26: =-Forutsetninger!$B$31*D23 | E26: =-Forutsetninger!$B$31*E23
A27: − Kostbase (trinnvis, rad 19) | B27: =-B19 | C27: =-C19 | D27: =-D19 | E27: =-E19
A28: RESULTAT med planlagt bemanning | B28: =B21+SUM(B24:B27) | C28: =C21+SUM(C24:C27) | D28: =D21+SUM(D24:D27) | E28: =E21+SUM(E24:E27)
A29: GAP mot resultatmål (negativt = mangler) | C29: =C28-C7 | D29: =D28-D7 | E29: =E28-E7
A30: Implisert nettomargin (informativ) | B30: =B28/B21 | C30: =C28/C21 | D30: =D28/D21 | E30: =E28/E21
A32: KVARTALSMÅL 2027 (regnet av bemanningsplanen for år 1 — rampen synlig)
B33: Q1 2027 | C33: Q2 2027 | D33: Q3 2027 | E33: Q4 2027
A34: Producing FTE i kvartalet | B34: =C10+C11*Forutsetninger!$B$20 | C34: =C10+C11*Forutsetninger!$B$21+C12*Forutsetninger!$B$20 | D34: =C10+C11*Forutsetninger!$B$22+C12*Forutsetninger!$B$21+C13*Forutsetninger!$B$20 | E34: =C10+C11*Forutsetninger!$B$22+C12*Forutsetninger!$B$22+C13*Forutsetninger!$B$21+C14*Forutsetninger!$B$20
A35: Omsetningsmål ex mva (FTE × stol/4 + Sindre/4) | B35: =(B34*Forutsetninger!$B$13+Forutsetninger!$B$14)/4 | C35: =(C34*Forutsetninger!$B$13+Forutsetninger!$B$14)/4 | D35: =(D34*Forutsetninger!$B$13+Forutsetninger!$B$14)/4 | E35: =(E34*Forutsetninger!$B$13+Forutsetninger!$B$14)/4
A36: Båter solgt | B36: =B35/Forutsetninger!$B$5 | C36: =C35/Forutsetninger!$B$5 | D36: =D35/Forutsetninger!$B$5 | E36: =E35/Forutsetninger!$B$5
A37: Signerte oppdrag inn | B37: =B36*Forutsetninger!$B$41 | C37: =C36*Forutsetninger!$B$41 | D37: =D36*Forutsetninger!$B$41 | E37: =E36*Forutsetninger!$B$41
A38: Kontroll: snittet av de fire kvartals-FTE-ene = årets FTE i rad 15. Summen av kvartalsomsetningen = rad 21 for år 1.
A40: BEHOV FOR MÅLET — selvkonsistent kostbase (flere stoler → høyere kostbase → mer omsetning …)
A41: Kostbasen avhenger av antall stoler, som avhenger av omsetningen. Fire scenarioer — modellen velger det som er konsistent med sitt eget stol-antall. (Steady-state: engangs rekrutteringskost holdes utenfor.)
A42: Scenario A (≤4 stoler): nødvendig megler-oms | C42: =(C7+Forutsetninger!$B$25-2*Forutsetninger!$B$26-(C8-MIN(Forutsetninger!$B$37*C8,Forutsetninger!$B$36)*Forutsetninger!$B$38-(Forutsetninger!$B$31*Forutsetninger!$B$41/Forutsetninger!$B$5)*C8))/(1-Forutsetninger!$B$34-(Forutsetninger!$B$31*Forutsetninger!$B$41/Forutsetninger!$B$5)-Forutsetninger!$B$26/Forutsetninger!$B$13) | D42: =(D7+Forutsetninger!$B$25-2*Forutsetninger!$B$26-(D8-MIN(Forutsetninger!$B$37*D8,Forutsetninger!$B$36)*Forutsetninger!$B$38-(Forutsetninger!$B$31*Forutsetninger!$B$41/Forutsetninger!$B$5)*D8))/(1-Forutsetninger!$B$34-(Forutsetninger!$B$31*Forutsetninger!$B$41/Forutsetninger!$B$5)-Forutsetninger!$B$26/Forutsetninger!$B$13) | E42: =(E7+Forutsetninger!$B$25-2*Forutsetninger!$B$26-(E8-MIN(Forutsetninger!$B$37*E8,Forutsetninger!$B$36)*Forutsetninger!$B$38-(Forutsetninger!$B$31*Forutsetninger!$B$41/Forutsetninger!$B$5)*E8))/(1-Forutsetninger!$B$34-(Forutsetninger!$B$31*Forutsetninger!$B$41/Forutsetninger!$B$5)-Forutsetninger!$B$26/Forutsetninger!$B$13)
A43: → producing FTE-behov A | C43: =C42/Forutsetninger!$B$13 | D43: =D42/Forutsetninger!$B$13 | E43: =E42/Forutsetninger!$B$13
A44: Scenario B (5 stoler, + salgsleder): megler-oms | C44: =(C7+Forutsetninger!$B$25-2*Forutsetninger!$B$26-(C8-MIN(Forutsetninger!$B$37*C8,Forutsetninger!$B$36)*Forutsetninger!$B$38-(Forutsetninger!$B$31*Forutsetninger!$B$41/Forutsetninger!$B$5)*C8)+Forutsetninger!$B$29)/(1-Forutsetninger!$B$34-(Forutsetninger!$B$31*Forutsetninger!$B$41/Forutsetninger!$B$5)-Forutsetninger!$B$26/Forutsetninger!$B$13) | D44: =(D7+Forutsetninger!$B$25-2*Forutsetninger!$B$26-(D8-MIN(Forutsetninger!$B$37*D8,Forutsetninger!$B$36)*Forutsetninger!$B$38-(Forutsetninger!$B$31*Forutsetninger!$B$41/Forutsetninger!$B$5)*D8)+Forutsetninger!$B$29)/(1-Forutsetninger!$B$34-(Forutsetninger!$B$31*Forutsetninger!$B$41/Forutsetninger!$B$5)-Forutsetninger!$B$26/Forutsetninger!$B$13) | E44: =(E7+Forutsetninger!$B$25-2*Forutsetninger!$B$26-(E8-MIN(Forutsetninger!$B$37*E8,Forutsetninger!$B$36)*Forutsetninger!$B$38-(Forutsetninger!$B$31*Forutsetninger!$B$41/Forutsetninger!$B$5)*E8)+Forutsetninger!$B$29)/(1-Forutsetninger!$B$34-(Forutsetninger!$B$31*Forutsetninger!$B$41/Forutsetninger!$B$5)-Forutsetninger!$B$26/Forutsetninger!$B$13)
A45: → producing FTE-behov B | C45: =C44/Forutsetninger!$B$13 | D45: =D44/Forutsetninger!$B$13 | E45: =E44/Forutsetninger!$B$13
A46: Scenario C (6–7 stoler, + leder + kontor): megler-oms | C46: =(C7+Forutsetninger!$B$25-2*Forutsetninger!$B$26-(C8-MIN(Forutsetninger!$B$37*C8,Forutsetninger!$B$36)*Forutsetninger!$B$38-(Forutsetninger!$B$31*Forutsetninger!$B$41/Forutsetninger!$B$5)*C8)+Forutsetninger!$B$29+Forutsetninger!$B$28)/(1-Forutsetninger!$B$34-(Forutsetninger!$B$31*Forutsetninger!$B$41/Forutsetninger!$B$5)-Forutsetninger!$B$26/Forutsetninger!$B$13) | D46: =(D7+Forutsetninger!$B$25-2*Forutsetninger!$B$26-(D8-MIN(Forutsetninger!$B$37*D8,Forutsetninger!$B$36)*Forutsetninger!$B$38-(Forutsetninger!$B$31*Forutsetninger!$B$41/Forutsetninger!$B$5)*D8)+Forutsetninger!$B$29+Forutsetninger!$B$28)/(1-Forutsetninger!$B$34-(Forutsetninger!$B$31*Forutsetninger!$B$41/Forutsetninger!$B$5)-Forutsetninger!$B$26/Forutsetninger!$B$13) | E46: =(E7+Forutsetninger!$B$25-2*Forutsetninger!$B$26-(E8-MIN(Forutsetninger!$B$37*E8,Forutsetninger!$B$36)*Forutsetninger!$B$38-(Forutsetninger!$B$31*Forutsetninger!$B$41/Forutsetninger!$B$5)*E8)+Forutsetninger!$B$29+Forutsetninger!$B$28)/(1-Forutsetninger!$B$34-(Forutsetninger!$B$31*Forutsetninger!$B$41/Forutsetninger!$B$5)-Forutsetninger!$B$26/Forutsetninger!$B$13)
A47: → producing FTE-behov C | C47: =C46/Forutsetninger!$B$13 | D47: =D46/Forutsetninger!$B$13 | E47: =E46/Forutsetninger!$B$13
A48: Scenario D (≥8 stoler, + leder + kontor + backoffice): megler-oms | C48: =(C7+Forutsetninger!$B$25-2*Forutsetninger!$B$26-(C8-MIN(Forutsetninger!$B$37*C8,Forutsetninger!$B$36)*Forutsetninger!$B$38-(Forutsetninger!$B$31*Forutsetninger!$B$41/Forutsetninger!$B$5)*C8)+Forutsetninger!$B$29+Forutsetninger!$B$28+Forutsetninger!$B$30)/(1-Forutsetninger!$B$34-(Forutsetninger!$B$31*Forutsetninger!$B$41/Forutsetninger!$B$5)-Forutsetninger!$B$26/Forutsetninger!$B$13) | D48: =(D7+Forutsetninger!$B$25-2*Forutsetninger!$B$26-(D8-MIN(Forutsetninger!$B$37*D8,Forutsetninger!$B$36)*Forutsetninger!$B$38-(Forutsetninger!$B$31*Forutsetninger!$B$41/Forutsetninger!$B$5)*D8)+Forutsetninger!$B$29+Forutsetninger!$B$28+Forutsetninger!$B$30)/(1-Forutsetninger!$B$34-(Forutsetninger!$B$31*Forutsetninger!$B$41/Forutsetninger!$B$5)-Forutsetninger!$B$26/Forutsetninger!$B$13) | E48: =(E7+Forutsetninger!$B$25-2*Forutsetninger!$B$26-(E8-MIN(Forutsetninger!$B$37*E8,Forutsetninger!$B$36)*Forutsetninger!$B$38-(Forutsetninger!$B$31*Forutsetninger!$B$41/Forutsetninger!$B$5)*E8)+Forutsetninger!$B$29+Forutsetninger!$B$28+Forutsetninger!$B$30)/(1-Forutsetninger!$B$34-(Forutsetninger!$B$31*Forutsetninger!$B$41/Forutsetninger!$B$5)-Forutsetninger!$B$26/Forutsetninger!$B$13)
A49: → producing FTE-behov D | C49: =C48/Forutsetninger!$B$13 | D49: =D48/Forutsetninger!$B$13 | E49: =E48/Forutsetninger!$B$13
A50: ENDELIG nødvendig megler-omsetning (konsistent scenario) | C50: =IF(ROUNDUP(C43,0)<=4,C42,IF(ROUNDUP(C45,0)<=5,C44,IF(ROUNDUP(C47,0)<=7,C46,C48))) | D50: =IF(ROUNDUP(D43,0)<=4,D42,IF(ROUNDUP(D45,0)<=5,D44,IF(ROUNDUP(D47,0)<=7,D46,D48))) | E50: =IF(ROUNDUP(E43,0)<=4,E42,IF(ROUNDUP(E45,0)<=5,E44,IF(ROUNDUP(E47,0)<=7,E46,E48)))
A51: ENDELIG nødvendig total omsetning | C51: =C50+C8 | D51: =D50+D8 | E51: =E50+E8
A52: ENDELIG producing FTE-behov (kapasitet, IKKE personer) | C52: =C50/Forutsetninger!$B$13 | D52: =D50/Forutsetninger!$B$13 | E52: =E50/Forutsetninger!$B$13
A53: Bemannede meglere for målet, steady-state (rundet opp + buffer) | C53: =ROUNDUP(C52,0)+Forutsetninger!$B$16 | D53: =ROUNDUP(D52,0)+Forutsetninger!$B$16 | E53: =ROUNDUP(E52,0)+Forutsetninger!$B$16
A54: Omsetningsgap (kapasitet − behov) | C54: =C21-C51 | D54: =D21-D51 | E54: =E21-E51
A55: FTE ≠ personer: i et INNFASINGSÅR yter nyansatte 40–100 % (rampen), så samme FTE krever flere bemannede — sammenlign rad 15 (FTE) mot rad 16 (bemannede) i planen. Scenario-tersklene (5/6/8) gjelder BEMANNEDE.
A57: Buffer-stolen har ingen kostnad i modellen (planlagt tom). Vinnraten 68 % brukes kun i aktivitetsnedbrytningen og er PROXY.
A58: Charter er holdt helt utenfor. Målt-kolonnen = fasit-omsetning m/dagens kostnivå og 7,1G — regnskapet 2025 viste +737k, se broen i Historikk.

Sheet 1-3-5 Plan
A1: HOUSE OF YACHTS — 1/3/5-ÅRSPLAN
A2: North Star: resultat før skatt (etter Sindre-lønn kappet på 7,1G). Mål og bemanning settes i Økonomimotor.
A3: Planen handler om stoler, ikke navn. Stol = rampet megler; Sindre egen stol; buffer = planlagt tom.
B5: Målt siste 12 mnd | C5: År 1 (2027) | D5: År 3 (2029) | E5: År 5 (2031)
A6: 1. NORTH STAR (fra Økonomimotor)
A7: Resultatmål før skatt | B7: =Økonomimotor!B7 | C7: =Økonomimotor!C7 | D7: =Økonomimotor!D7 | E7: =Økonomimotor!E7
A8: Omsetning målet krever (behov) | B8: =Økonomimotor!B21 | C8: =Økonomimotor!C51 | D8: =Økonomimotor!D51 | E8: =Økonomimotor!E51
A9: Kapasitet med planlagt bemanning | C9: =Økonomimotor!C21 | D9: =Økonomimotor!D21 | E9: =Økonomimotor!E21
A10: Resultat med planlagt bemanning / GAP mot mål | B10: =Økonomimotor!B28 | C10: =Økonomimotor!C29 | D10: =Økonomimotor!D29 | E10: =Økonomimotor!E29
A12: 2. FRA OMSETNING TIL BÅTER (behov)
A13: Inntekt per solgt båt, ex mva (fasit) | B13: =Forutsetninger!$B$5 | C13: =Forutsetninger!$B$5 | D13: =Forutsetninger!$B$5 | E13: =Forutsetninger!$B$5
A14: Båter som må selges per år | B14: 75 | C14: =C8/Forutsetninger!$B$5 | D14: =D8/Forutsetninger!$B$5 | E14: =E8/Forutsetninger!$B$5
A15: Båter per måned | B15: =B14/12 | C15: =C14/12 | D15: =D14/12 | E15: =E14/12
A17: 3. FRA BÅTER TIL STOLER
A18: Producing megler-FTE målet krever | C18: =Økonomimotor!C52 | D18: =Økonomimotor!D52 | E18: =Økonomimotor!E52
A19: Planlagt producing FTE (bemanningsplan m/ramp) | B19: 1 | C19: =Økonomimotor!C15 | D19: =Økonomimotor!D15 | E19: =Økonomimotor!E15
A20: Megler-stoler å bemanne for målet (rundet opp + buffer) | C20: =Økonomimotor!C53 | D20: =Økonomimotor!D53 | E20: =Økonomimotor!E53
A21: Planlagt bemannet ved årets slutt | B21: =Forutsetninger!$B$17 | C21: =Økonomimotor!C16 | D21: =Økonomimotor!D16 | E21: =Økonomimotor!E16
A22: REKRUTTERINGSGAP mot målet (stoler) | C22: =C20-C21 | D22: =D20-D21 | E22: =E20-E21
A24: 4. FRA STOLER TIL UKENTLIGE AKTIVITETER (behov; 68 % er PROXY)
A25: Signerte oppdrag inn per år (båter × 1,30 planantakelse) | B25: 67 | C25: =C14*Forutsetninger!$B$41 | D25: =D14*Forutsetninger!$B$41 | E25: =E14*Forutsetninger!$B$41
A26: Signerte oppdrag per uke | B26: =B25/Forutsetninger!$B$44 | C26: =C25/Forutsetninger!$B$44 | D26: =D25/Forutsetninger!$B$44 | E26: =E25/Forutsetninger!$B$44
A27: Befaringer per år (÷ 68 % PROXY-vinnrate) | B27: =B25/Forutsetninger!$B$42 | C27: =C25/Forutsetninger!$B$42 | D27: =D25/Forutsetninger!$B$42 | E27: =E25/Forutsetninger!$B$42
A28: Befaringer per uke (teamet) | B28: =B27/Forutsetninger!$B$44 | C28: =C27/Forutsetninger!$B$44 | D28: =D27/Forutsetninger!$B$44 | E28: =E27/Forutsetninger!$B$44
A29: Kvalifiserte prospects per år (÷ 50 %) | B29: 133 | C29: =C27/Forutsetninger!$B$43 | D29: =D27/Forutsetninger!$B$43 | E29: =E27/Forutsetninger!$B$43
A30: Nye prospects per uke (teamet) | B30: =B29/Forutsetninger!$B$44 | C30: =C29/Forutsetninger!$B$44 | D30: =D29/Forutsetninger!$B$44 | E30: =E29/Forutsetninger!$B$44
A31: Befaringer per uke PER planlagt FTE (inkl. Sindre) | B31: =B28/(B19+1) | C31: =C28/(C19+1) | D31: =D28/(D19+1) | E31: =E28/(E19+1)
A33: Når en megler slutter: rør ikke målene. Oppdater bemanningsplanen i Økonomimotor + «bemannet i dag» i Forutsetninger.
A34: Rekrutteringsgapet og resultat-gapet oppdaterer seg selv — det er de to tallene ukemøtet skal styre på.

Sheet Spaker
A1: SPAKER — samme bemanningsplan, bedre driftsøkonomi
A2: Scenario: provisjonsdisiplin ≥6 %/45k + premium-miks (snittbåt mot 1,6M), markedskost-tak, sterkere stoler (1,8M).
A4: Scenario-parametre (blå = juster):
A5: Inntekt per båt ex mva (1,6M snittbåt × 6 % ÷ 1,25) | B5: 76800
A6: Markedskost per signert oppdrag (CFO-mål) | B6: 4552
A7: Omsetning per producing megler-stol (produksjonsmål) | B7: 1800000
C9: År 1 (2027) | D9: År 3 (2029) | E9: År 5 (2031)
A10: Resultatmål (fra Økonomimotor) | C10: =Økonomimotor!C7 | D10: =Økonomimotor!D7 | E10: =Økonomimotor!E7
A11: Kapasitets-omsetning m/spakene (samme FTE, 1,8M-stoler) | C11: =Økonomimotor!C15*$B$7+Økonomimotor!C8 | D11: =Økonomimotor!D15*$B$7+Økonomimotor!D8 | E11: =Økonomimotor!E15*$B$7+Økonomimotor!E8
A12: − Meglerkost 55 % av megler-oms | C12: =-Forutsetninger!$B$34*(C11-Økonomimotor!C8) | D12: =-Forutsetninger!$B$34*(D11-Økonomimotor!D8) | E12: =-Forutsetninger!$B$34*(E11-Økonomimotor!E8)
A13: − Sindre-kompensasjon (7,1G, loaded) | C13: =-MIN(Forutsetninger!$B$37*Økonomimotor!C8,Forutsetninger!$B$36)*Forutsetninger!$B$38 | D13: =-MIN(Forutsetninger!$B$37*Økonomimotor!D8,Forutsetninger!$B$36)*Forutsetninger!$B$38 | E13: =-MIN(Forutsetninger!$B$37*Økonomimotor!E8,Forutsetninger!$B$36)*Forutsetninger!$B$38
A14: − Markedskost (oms ÷ 76 800 × 1,30 × 4 552) | B14: (færre båter per krone enn baseline!) | C14: =-$B$6*(C11/$B$5*Forutsetninger!$B$41) | D14: =-$B$6*(D11/$B$5*Forutsetninger!$B$41) | E14: =-$B$6*(E11/$B$5*Forutsetninger!$B$41)
A15: − Kostbase (samme trinnkost som motoren, rad 19) | C15: =-Økonomimotor!C19 | D15: =-Økonomimotor!D19 | E15: =-Økonomimotor!E19
A16: RESULTAT m/spakene på planlagt bemanning | C16: =C11+SUM(C12:C15) | D16: =D11+SUM(D12:D15) | E16: =E11+SUM(E12:E15)
A17: KONTROLL: linjene minus resultat (skal være 0) | C17: =(C11+C12+C13+C14+C15)-C16 | D17: =(D11+D12+D13+D14+D15)-D16 | E17: =(E11+E12+E13+E14+E15)-E16
A18: Resultat baseline (Økonomimotor) | C18: =Økonomimotor!C28 | D18: =Økonomimotor!D28 | E18: =Økonomimotor!E28
A19: Spak-effekt på resultatet | C19: =C16-C18 | D19: =D16-D18 | E19: =E16-E18
A21: BEHOV FOR MÅLET M/SPAKENE — selvkonsistent, samme metode som motoren. NB: FTE = produksjonskapasitet, IKKE personer.
A22: Scenario A (≤4 bemannede): nødvendig megler-oms | C22: =(Økonomimotor!C7+Forutsetninger!$B$25-2*Forutsetninger!$B$26-(Økonomimotor!C8-MIN(Forutsetninger!$B$37*Økonomimotor!C8,Forutsetninger!$B$36)*Forutsetninger!$B$38-($B$6*Forutsetninger!$B$41/$B$5)*Økonomimotor!C8))/(1-Forutsetninger!$B$34-($B$6*Forutsetninger!$B$41/$B$5)-Forutsetninger!$B$26/$B$7) | D22: =(Økonomimotor!D7+Forutsetninger!$B$25-2*Forutsetninger!$B$26-(Økonomimotor!D8-MIN(Forutsetninger!$B$37*Økonomimotor!D8,Forutsetninger!$B$36)*Forutsetninger!$B$38-($B$6*Forutsetninger!$B$41/$B$5)*Økonomimotor!D8))/(1-Forutsetninger!$B$34-($B$6*Forutsetninger!$B$41/$B$5)-Forutsetninger!$B$26/$B$7) | E22: =(Økonomimotor!E7+Forutsetninger!$B$25-2*Forutsetninger!$B$26-(Økonomimotor!E8-MIN(Forutsetninger!$B$37*Økonomimotor!E8,Forutsetninger!$B$36)*Forutsetninger!$B$38-($B$6*Forutsetninger!$B$41/$B$5)*Økonomimotor!E8))/(1-Forutsetninger!$B$34-($B$6*Forutsetninger!$B$41/$B$5)-Forutsetninger!$B$26/$B$7)
A23: → producing FTE-behov A | C23: =C22/$B$7 | D23: =D22/$B$7 | E23: =E22/$B$7
A24: Scenario B (5 bemannede, +leder): megler-oms | C24: =(Økonomimotor!C7+Forutsetninger!$B$25-2*Forutsetninger!$B$26-(Økonomimotor!C8-MIN(Forutsetninger!$B$37*Økonomimotor!C8,Forutsetninger!$B$36)*Forutsetninger!$B$38-($B$6*Forutsetninger!$B$41/$B$5)*Økonomimotor!C8)+Forutsetninger!$B$29)/(1-Forutsetninger!$B$34-($B$6*Forutsetninger!$B$41/$B$5)-Forutsetninger!$B$26/$B$7) | D24: =(Økonomimotor!D7+Forutsetninger!$B$25-2*Forutsetninger!$B$26-(Økonomimotor!D8-MIN(Forutsetninger!$B$37*Økonomimotor!D8,Forutsetninger!$B$36)*Forutsetninger!$B$38-($B$6*Forutsetninger!$B$41/$B$5)*Økonomimotor!D8)+Forutsetninger!$B$29)/(1-Forutsetninger!$B$34-($B$6*Forutsetninger!$B$41/$B$5)-Forutsetninger!$B$26/$B$7) | E24: =(Økonomimotor!E7+Forutsetninger!$B$25-2*Forutsetninger!$B$26-(Økonomimotor!E8-MIN(Forutsetninger!$B$37*Økonomimotor!E8,Forutsetninger!$B$36)*Forutsetninger!$B$38-($B$6*Forutsetninger!$B$41/$B$5)*Økonomimotor!E8)+Forutsetninger!$B$29)/(1-Forutsetninger!$B$34-($B$6*Forutsetninger!$B$41/$B$5)-Forutsetninger!$B$26/$B$7)
A25: → producing FTE-behov B | C25: =C24/$B$7 | D25: =D24/$B$7 | E25: =E24/$B$7
A26: Scenario C (6–7, +leder+kontor): megler-oms | C26: =(Økonomimotor!C7+Forutsetninger!$B$25-2*Forutsetninger!$B$26-(Økonomimotor!C8-MIN(Forutsetninger!$B$37*Økonomimotor!C8,Forutsetninger!$B$36)*Forutsetninger!$B$38-($B$6*Forutsetninger!$B$41/$B$5)*Økonomimotor!C8)+Forutsetninger!$B$29+Forutsetninger!$B$28)/(1-Forutsetninger!$B$34-($B$6*Forutsetninger!$B$41/$B$5)-Forutsetninger!$B$26/$B$7) | D26: =(Økonomimotor!D7+Forutsetninger!$B$25-2*Forutsetninger!$B$26-(Økonomimotor!D8-MIN(Forutsetninger!$B$37*Økonomimotor!D8,Forutsetninger!$B$36)*Forutsetninger!$B$38-($B$6*Forutsetninger!$B$41/$B$5)*Økonomimotor!D8)+Forutsetninger!$B$29+Forutsetninger!$B$28)/(1-Forutsetninger!$B$34-($B$6*Forutsetninger!$B$41/$B$5)-Forutsetninger!$B$26/$B$7) | E26: =(Økonomimotor!E7+Forutsetninger!$B$25-2*Forutsetninger!$B$26-(Økonomimotor!E8-MIN(Forutsetninger!$B$37*Økonomimotor!E8,Forutsetninger!$B$36)*Forutsetninger!$B$38-($B$6*Forutsetninger!$B$41/$B$5)*Økonomimotor!E8)+Forutsetninger!$B$29+Forutsetninger!$B$28)/(1-Forutsetninger!$B$34-($B$6*Forutsetninger!$B$41/$B$5)-Forutsetninger!$B$26/$B$7)
A27: → producing FTE-behov C | C27: =C26/$B$7 | D27: =D26/$B$7 | E27: =E26/$B$7
A28: Scenario D (≥8, +leder+kontor+backoffice): megler-oms | C28: =(Økonomimotor!C7+Forutsetninger!$B$25-2*Forutsetninger!$B$26-(Økonomimotor!C8-MIN(Forutsetninger!$B$37*Økonomimotor!C8,Forutsetninger!$B$36)*Forutsetninger!$B$38-($B$6*Forutsetninger!$B$41/$B$5)*Økonomimotor!C8)+Forutsetninger!$B$29+Forutsetninger!$B$28+Forutsetninger!$B$30)/(1-Forutsetninger!$B$34-($B$6*Forutsetninger!$B$41/$B$5)-Forutsetninger!$B$26/$B$7) | D28: =(Økonomimotor!D7+Forutsetninger!$B$25-2*Forutsetninger!$B$26-(Økonomimotor!D8-MIN(Forutsetninger!$B$37*Økonomimotor!D8,Forutsetninger!$B$36)*Forutsetninger!$B$38-($B$6*Forutsetninger!$B$41/$B$5)*Økonomimotor!D8)+Forutsetninger!$B$29+Forutsetninger!$B$28+Forutsetninger!$B$30)/(1-Forutsetninger!$B$34-($B$6*Forutsetninger!$B$41/$B$5)-Forutsetninger!$B$26/$B$7) | E28: =(Økonomimotor!E7+Forutsetninger!$B$25-2*Forutsetninger!$B$26-(Økonomimotor!E8-MIN(Forutsetninger!$B$37*Økonomimotor!E8,Forutsetninger!$B$36)*Forutsetninger!$B$38-($B$6*Forutsetninger!$B$41/$B$5)*Økonomimotor!E8)+Forutsetninger!$B$29+Forutsetninger!$B$28+Forutsetninger!$B$30)/(1-Forutsetninger!$B$34-($B$6*Forutsetninger!$B$41/$B$5)-Forutsetninger!$B$26/$B$7)
A29: → producing FTE-behov D | C29: =C28/$B$7 | D29: =D28/$B$7 | E29: =E28/$B$7
A30: ENDELIG nødvendig total omsetning m/spakene | B30: (konsistent scenario) | C30: =IF(ROUNDUP(C23,0)<=4,C22,IF(ROUNDUP(C25,0)<=5,C24,IF(ROUNDUP(C27,0)<=7,C26,C28)))+Økonomimotor!C8 | D30: =IF(ROUNDUP(D23,0)<=4,D22,IF(ROUNDUP(D25,0)<=5,D24,IF(ROUNDUP(D27,0)<=7,D26,D28)))+Økonomimotor!D8 | E30: =IF(ROUNDUP(E23,0)<=4,E22,IF(ROUNDUP(E25,0)<=5,E24,IF(ROUNDUP(E27,0)<=7,E26,E28)))+Økonomimotor!E8
A31: ENDELIG producing FTE-behov m/spakene | C31: =(C30-Økonomimotor!C8)/$B$7 | D31: =(D30-Økonomimotor!D8)/$B$7 | E31: =(E30-Økonomimotor!E8)/$B$7
A32: Bemannede meglere, steady-state (rundet opp) | B32: (rampede — i INNFASINGSÅR trengs flere pga ramp) | C32: =ROUNDUP(C31,0) | D32: =ROUNDUP(D31,0) | E32: =ROUNDUP(E31,0)
A33: Producing FTE-behov baseline (Økonomimotor) | C33: =Økonomimotor!C52 | D33: =Økonomimotor!D52 | E33: =Økonomimotor!E52
A36: DE FIRE SPAKENE (CFO-analysen jul 2026) — verdt å hente FØR flere stoler rekrutteres:
A37: A. Provisjonsdisiplin: 13 av 38 H1-salg under 6 %/45k = ~266k tapt provisjon. Rabatt krever Sindres godkjenning. ~200k+/år.
A38: B. Marte-tripwire (18. okt): Henrik må vise 1,9M+ årstakt og bedre befaring-rate. Svinger resultatet 500–700k. Status aug: behold.
A39: C. Markedskost-tak: 15k-tak håndheves; frys markedsføring over taket til pris justeres. Mål 4 552/oppdrag (målt 6 600).
A40: D. Sindres 7,1G-uttak: alt Sindre omsetter over ~2,15M koster ikke mer lønn — hans marginale omsetning er firmaets mest lønnsomme.
A41: E. (Ny) Premium-miks: fasit-snittet er 58 375/båt (median 50 400). Hver 10 000 kr høyere inntekt/båt ≈ 15–20 % færre båter for samme mål.

Sheet Likviditet
A1: LIKVIDITET — månedlig kontantstrøm jan 2027 – des 2028
A2: Samme motor som resten av boka (Forutsetninger). GUL = ditt valg. Ferske åpningstall per 28.08.2026. Alt merket ANSLAG/PLASSHOLDER kan justeres fritt.
A3: NØKKELTALL (regnes av tabellen under)
A4: Laveste kontantsaldo i perioden | B4: =MIN(B102:Y102)
A5: — inntreffer i måned | B5: =INDEX(B53:Y53,1,MATCH(MIN(B102:Y102),B102:Y102,0))
A6: Margin mot minimumsbuffer på lavpunktet | B6: =MIN(B102:Y102)-$B$29
A7: Antall måneder under bufferen | B7: =COUNTIF(B102:Y102,"<"&$B$29)
A8: Laveste saldo + kassekreditt (bunn før overtrekk) | B8: =MIN(B102:Y102)+$B$30
A9: Kontantsaldo ved utgangen (des 2028) | B9: =Y102
A11: FERSKE TALL FRA POWEROFFICE (hentet 2026-08-29 — oppdateres nattlig)
A12: Bank — PowerOffice-hovedbok (alle 19xx) | B12: -289975 | C12: AVSTEMMING: sammenlign med reell banksaldo i A. Stort avvik = uposterte bilag (hovedboka henger etter).
A13: Kundefordringer (hovedbok 15xx) | B13: 1429008 | C13: Utestående kundefordringer. Åpne poster (reell AR): 1 429 008
A14: Leverandørgjeld (24xx) | B14: -17130 | C14: Negativt = gjeld.
A15: Utgående mva-gjeld (27xx) | B15: -578155 | C15: Negativt = skyldig mva. Betales ved neste termin (i praksis i Q4 2026 — del av bro sep–des).
A16: Skyldig skattetrekk (26xx) | B16: 0 | C16: Bundet på skattetrekkskonto.
A17: Betalbar skatt (25xx) | B17: 14636
A18: Driftskost annualisert (6xxx+7xxx, u/lønn) | B18: 262779 | C18: Fra 14 mnd posteringer × 12. Lønn (5xxx) = 1 002 310 i vinduet (inkl. megler+Marte+Philip — må splittes før kostbase-kalibrering).
A19: Grønne tall hentes automatisk fra PowerOffice hver gang boka bygges. De er FERSK POSISJON i dag (28.08) — modellen starter jan 2027, så bruk dem til å sette broen sep–des 2026 og overheng, ikke som direkte januartall.
A21: A. ÅPNINGSPOSISJON OG STYRINGSVALG
A22: Hovedbok 1920 — bank (live fra PowerOffice) | B22: -289978 | C22: Bokført banksaldo (henger etter reell bank med differansen under).
A23: + Avstemmingsdifferanse (kontoutskrift − hovedbok 1920) | B23: 1360037 | C23: Fra PO bankavstemming 14.09.2026: 1 069 274 − (−290 763) = 1 360 037. Frossen historisk differanse (avstemmingen viser «Sum bevegelser 0»). Oppdater fra GO-rapporten ved behov.
A24: =Reell banksaldo (kontoutskrift) | B24: =$B$22+$B$23 | C24: =hovedbok 1920 + differanse ≈ «Saldo kontoutskrift» i GO. Oppdateres live når 1920 synkes. UTEN kassekreditt (se under).
A25: — herav bundet skattetrekk (utilgjengelig) | B25: 0 | C25: Auto fra PowerOffice (konto 26xx).
A26: Disponibel saldo i dag | B26: =$B$24-$B$25
A27: Netto driftskontantstrøm sep–des 2026 (bro til nyttår) | B27: 0 | C27: PLASSHOLDER. Netto inn−ut sep–des 2026 EKSKL. provisjon som først innbetales i 2027 (ligger i «overheng» under).
A28: =ÅPNINGSSALDO 1. jan 2027 | B28: =$B$26+$B$27
A29: Minimumsbuffer (ønsket bunnivå på konto) | B29: 500000 | C29: Ditt valg. Modellen flagger måneder under dette.
A30: Tilgjengelig kassekreditt (overtrekksramme) | B30: 200000 | C30: Ekstra likviditet på toppen — kontoutskrift-saldoen er UTEN denne. Reell bunn før overtrekk = −kassekreditt.
A31: Cash-lag scenario (1=Base median ~14d · 2=Plan P75 ~32d · 3=Stress P90 ~61d) | B31: 1 | C31: DOKUMENTERT deal-for-deal (solgt→faktura, n=92, se deal-for-deal-oppgjor.csv): median 14d, P75 32d, P90 61d, maks 116. Andel betalt innen 7/14/30/60d = 23/51/75/89 %. FOR ANSETTELSESBESLUTNINGER: bruk Plan (P75=2). NB (rådgiver): fakturadato brukes som OPERATIV cash-proxy fordi provisjonen normalt er tilgjengelig ved oppgjør — dette må avstemmes mot FAKTISK bankdato. Bokført betalt ligger i flere tilfeller 50–100 d etter faktura (bevis bokføringsetterslep, ikke at cash var tilgjengelig samme dag). Hent bankdato for de store oppgjørene.
A32: Sesongprofil på salg (1=empirisk · 0=flatt 1/12) | B32: 1 | C32: 1 = fordel salget som FAKTISK målt (mai–jul tungt, vinter tynt). 0 = jevnt.
A33: Markedsføring betales N mnd FØR salget | B33: 3 | C33: Annonsering/foto betales når oppdraget signeres, ~89 dg (3 mnd) før salg.
A34: Meglerutbetaling N mnd etter salg | B34: 0 | C34: 0 = megler får oppgjør samme måned som salget (konservativt).
A35: Mva-sats (utgående/inngående) | B35: 0.25 | C35: Standard 25 %.
A36: Mva-belagt andel av kostbasen | B36: 0.35 | C36: PLANANTAKELSE: andel av kostbasen (ekskl. lønn) med inngående mva.
A38: B. BETALINGSPROFIL — andel av en salgsmåneds provisjon innbetalt m/forsinkelse
A39: Profil | B39: salgsmnd | C39: +1 mnd | D39: +2 mnd | E39: +3 mnd | F39: +4 mnd | G39: snitt (dg)
A40: 1 Base — faktisk median (~14d) | B40: 0.54 | C40: 0.3 | D40: 0.1 | E40: 0.03 | F40: 0.03 | G40: =(C40*1+D40*2+E40*3+F40*4)*30.4
A41: 2 Plan — P75 (~32d) | B41: 0.3 | C41: 0.4 | D41: 0.2 | E41: 0.07 | F41: 0.03 | G41: =(C41*1+D41*2+E41*3+F41*4)*30.4
A42: 3 Stress — P90 (~61d) | B42: 0.1 | C42: 0.25 | D42: 0.4 | E42: 0.2 | F42: 0.05 | G42: =(C42*1+D42*2+E42*3+F42*4)*30.4
A43: AKTIV PROFIL (valgt av scenario over) | B43: =CHOOSE($B$31,B40,B41,B42) | C43: =CHOOSE($B$31,C40,C41,C42) | D43: =CHOOSE($B$31,D40,D41,D42) | E43: =CHOOSE($B$31,E40,E41,E42) | F43: =CHOOSE($B$31,F40,F41,F42) | G43: =SUM(B43:F43)
A44: Kontroll: aktiv profil = 100 % | B44: =SUM(B43:F43)
A46: C. SESONGINDEKS — månedsandel av årets provisjon (FAKTISK målt, oppgjør 2025+2026)
B47: jan | C47: feb | D47: mar | E47: apr | F47: mai | G47: jun | H47: jul | I47: aug | J47: sep | K47: okt | L47: nov | M47: des
A48: Andel av årsprovisjon per måned | B48: 0.03 | C48: 0.0524 | D48: 0.0874 | E48: 0.0554 | F48: 0.1728 | G48: 0.2095 | H48: 0.1457 | I48: 0.0554 | J48: 0.0816 | K48: 0.034 | L48: 0.0447 | M48: 0.0311
A49: Kontroll: summerer til 100 % | B49: =SUM(B48:M48) | D49: jan≈0 i rådata (lite utvalg) → 3 % gulv + renormalisert. Mai–jul ≈ 53 % av året.
A51: D. BEMANNING → PRODUKSJONSKAPASITET (samme ramp som motoren)
A52: Oppstartsmåned per stol (GUL, i «start»-kolonnen ytterst). 1 = jan 2027 … 24 = des 2028. Negativt = allerede rampet. Tom = ledig. Ramp mnd 1–3=40 %, 4–6=75 %, 7+=100 % (Forutsetninger).
A53: Stol \ måned → | B53: jan 27 | C53: feb 27 | D53: mar 27 | E53: apr 27 | F53: mai 27 | G53: jun 27 | H53: jul 27 | I53: aug 27 | J53: sep 27 | K53: okt 27 | L53: nov 27 | M53: des 27 | N53: jan 28 | O53: feb 28 | P53: mar 28 | Q53: apr 28 | R53: mai 28 | S53: jun 28 | T53: jul 28 | U53: aug 28 | V53: sep 28 | W53: okt 28 | X53: nov 28 | Y53: des 28 | Z53: start
A54: Megler-stol 1 (Henrik — rampet) | B54: =IF($Z$54="",0,IF(1<$Z$54,0,IF(1-$Z$54<3,Forutsetninger!$B$20,IF(1-$Z$54<6,Forutsetninger!$B$21,Forutsetninger!$B$22)))) | C54: =IF($Z$54="",0,IF(2<$Z$54,0,IF(2-$Z$54<3,Forutsetninger!$B$20,IF(2-$Z$54<6,Forutsetninger!$B$21,Forutsetninger!$B$22)))) | D54: =IF($Z$54="",0,IF(3<$Z$54,0,IF(3-$Z$54<3,Forutsetninger!$B$20,IF(3-$Z$54<6,Forutsetninger!$B$21,Forutsetninger!$B$22)))) | E54: =IF($Z$54="",0,IF(4<$Z$54,0,IF(4-$Z$54<3,Forutsetninger!$B$20,IF(4-$Z$54<6,Forutsetninger!$B$21,Forutsetninger!$B$22)))) | F54: =IF($Z$54="",0,IF(5<$Z$54,0,IF(5-$Z$54<3,Forutsetninger!$B$20,IF(5-$Z$54<6,Forutsetninger!$B$21,Forutsetninger!$B$22)))) | G54: =IF($Z$54="",0,IF(6<$Z$54,0,IF(6-$Z$54<3,Forutsetninger!$B$20,IF(6-$Z$54<6,Forutsetninger!$B$21,Forutsetninger!$B$22)))) | H54: =IF($Z$54="",0,IF(7<$Z$54,0,IF(7-$Z$54<3,Forutsetninger!$B$20,IF(7-$Z$54<6,Forutsetninger!$B$21,Forutsetninger!$B$22)))) | I54: =IF($Z$54="",0,IF(8<$Z$54,0,IF(8-$Z$54<3,Forutsetninger!$B$20,IF(8-$Z$54<6,Forutsetninger!$B$21,Forutsetninger!$B$22)))) | J54: =IF($Z$54="",0,IF(9<$Z$54,0,IF(9-$Z$54<3,Forutsetninger!$B$20,IF(9-$Z$54<6,Forutsetninger!$B$21,Forutsetninger!$B$22)))) | K54: =IF($Z$54="",0,IF(10<$Z$54,0,IF(10-$Z$54<3,Forutsetninger!$B$20,IF(10-$Z$54<6,Forutsetninger!$B$21,Forutsetninger!$B$22)))) | L54: =IF($Z$54="",0,IF(11<$Z$54,0,IF(11-$Z$54<3,Forutsetninger!$B$20,IF(11-$Z$54<6,Forutsetninger!$B$21,Forutsetninger!$B$22)))) | M54: =IF($Z$54="",0,IF(12<$Z$54,0,IF(12-$Z$54<3,Forutsetninger!$B$20,IF(12-$Z$54<6,Forutsetninger!$B$21,Forutsetninger!$B$22)))) | N54: =IF($Z$54="",0,IF(13<$Z$54,0,IF(13-$Z$54<3,Forutsetninger!$B$20,IF(13-$Z$54<6,Forutsetninger!$B$21,Forutsetninger!$B$22)))) | O54: =IF($Z$54="",0,IF(14<$Z$54,0,IF(14-$Z$54<3,Forutsetninger!$B$20,IF(14-$Z$54<6,Forutsetninger!$B$21,Forutsetninger!$B$22)))) | P54: =IF($Z$54="",0,IF(15<$Z$54,0,IF(15-$Z$54<3,Forutsetninger!$B$20,IF(15-$Z$54<6,Forutsetninger!$B$21,Forutsetninger!$B$22)))) | Q54: =IF($Z$54="",0,IF(16<$Z$54,0,IF(16-$Z$54<3,Forutsetninger!$B$20,IF(16-$Z$54<6,Forutsetninger!$B$21,Forutsetninger!$B$22)))) | R54: =IF($Z$54="",0,IF(17<$Z$54,0,IF(17-$Z$54<3,Forutsetninger!$B$20,IF(17-$Z$54<6,Forutsetninger!$B$21,Forutsetninger!$B$22)))) | S54: =IF($Z$54="",0,IF(18<$Z$54,0,IF(18-$Z$54<3,Forutsetninger!$B$20,IF(18-$Z$54<6,Forutsetninger!$B$21,Forutsetninger!$B$22)))) | T54: =IF($Z$54="",0,IF(19<$Z$54,0,IF(19-$Z$54<3,Forutsetninger!$B$20,IF(19-$Z$54<6,Forutsetninger!$B$21,Forutsetninger!$B$22)))) | U54: =IF($Z$54="",0,IF(20<$Z$54,0,IF(20-$Z$54<3,Forutsetninger!$B$20,IF(20-$Z$54<6,Forutsetninger!$B$21,Forutsetninger!$B$22)))) | V54: =IF($Z$54="",0,IF(21<$Z$54,0,IF(21-$Z$54<3,Forutsetninger!$B$20,IF(21-$Z$54<6,Forutsetninger!$B$21,Forutsetninger!$B$22)))) | W54: =IF($Z$54="",0,IF(22<$Z$54,0,IF(22-$Z$54<3,Forutsetninger!$B$20,IF(22-$Z$54<6,Forutsetninger!$B$21,Forutsetninger!$B$22)))) | X54: =IF($Z$54="",0,IF(23<$Z$54,0,IF(23-$Z$54<3,Forutsetninger!$B$20,IF(23-$Z$54<6,Forutsetninger!$B$21,Forutsetninger!$B$22)))) | Y54: =IF($Z$54="",0,IF(24<$Z$54,0,IF(24-$Z$54<3,Forutsetninger!$B$20,IF(24-$Z$54<6,Forutsetninger!$B$21,Forutsetninger!$B$22)))) | Z54: -6
A55: Megler-stol 2 (rampet ved 2027-start) | B55: =IF($Z$55="",0,IF(1<$Z$55,0,IF(1-$Z$55<3,Forutsetninger!$B$20,IF(1-$Z$55<6,Forutsetninger!$B$21,Forutsetninger!$B$22)))) | C55: =IF($Z$55="",0,IF(2<$Z$55,0,IF(2-$Z$55<3,Forutsetninger!$B$20,IF(2-$Z$55<6,Forutsetninger!$B$21,Forutsetninger!$B$22)))) | D55: =IF($Z$55="",0,IF(3<$Z$55,0,IF(3-$Z$55<3,Forutsetninger!$B$20,IF(3-$Z$55<6,Forutsetninger!$B$21,Forutsetninger!$B$22)))) | E55: =IF($Z$55="",0,IF(4<$Z$55,0,IF(4-$Z$55<3,Forutsetninger!$B$20,IF(4-$Z$55<6,Forutsetninger!$B$21,Forutsetninger!$B$22)))) | F55: =IF($Z$55="",0,IF(5<$Z$55,0,IF(5-$Z$55<3,Forutsetninger!$B$20,IF(5-$Z$55<6,Forutsetninger!$B$21,Forutsetninger!$B$22)))) | G55: =IF($Z$55="",0,IF(6<$Z$55,0,IF(6-$Z$55<3,Forutsetninger!$B$20,IF(6-$Z$55<6,Forutsetninger!$B$21,Forutsetninger!$B$22)))) | H55: =IF($Z$55="",0,IF(7<$Z$55,0,IF(7-$Z$55<3,Forutsetninger!$B$20,IF(7-$Z$55<6,Forutsetninger!$B$21,Forutsetninger!$B$22)))) | I55: =IF($Z$55="",0,IF(8<$Z$55,0,IF(8-$Z$55<3,Forutsetninger!$B$20,IF(8-$Z$55<6,Forutsetninger!$B$21,Forutsetninger!$B$22)))) | J55: =IF($Z$55="",0,IF(9<$Z$55,0,IF(9-$Z$55<3,Forutsetninger!$B$20,IF(9-$Z$55<6,Forutsetninger!$B$21,Forutsetninger!$B$22)))) | K55: =IF($Z$55="",0,IF(10<$Z$55,0,IF(10-$Z$55<3,Forutsetninger!$B$20,IF(10-$Z$55<6,Forutsetninger!$B$21,Forutsetninger!$B$22)))) | L55: =IF($Z$55="",0,IF(11<$Z$55,0,IF(11-$Z$55<3,Forutsetninger!$B$20,IF(11-$Z$55<6,Forutsetninger!$B$21,Forutsetninger!$B$22)))) | M55: =IF($Z$55="",0,IF(12<$Z$55,0,IF(12-$Z$55<3,Forutsetninger!$B$20,IF(12-$Z$55<6,Forutsetninger!$B$21,Forutsetninger!$B$22)))) | N55: =IF($Z$55="",0,IF(13<$Z$55,0,IF(13-$Z$55<3,Forutsetninger!$B$20,IF(13-$Z$55<6,Forutsetninger!$B$21,Forutsetninger!$B$22)))) | O55: =IF($Z$55="",0,IF(14<$Z$55,0,IF(14-$Z$55<3,Forutsetninger!$B$20,IF(14-$Z$55<6,Forutsetninger!$B$21,Forutsetninger!$B$22)))) | P55: =IF($Z$55="",0,IF(15<$Z$55,0,IF(15-$Z$55<3,Forutsetninger!$B$20,IF(15-$Z$55<6,Forutsetninger!$B$21,Forutsetninger!$B$22)))) | Q55: =IF($Z$55="",0,IF(16<$Z$55,0,IF(16-$Z$55<3,Forutsetninger!$B$20,IF(16-$Z$55<6,Forutsetninger!$B$21,Forutsetninger!$B$22)))) | R55: =IF($Z$55="",0,IF(17<$Z$55,0,IF(17-$Z$55<3,Forutsetninger!$B$20,IF(17-$Z$55<6,Forutsetninger!$B$21,Forutsetninger!$B$22)))) | S55: =IF($Z$55="",0,IF(18<$Z$55,0,IF(18-$Z$55<3,Forutsetninger!$B$20,IF(18-$Z$55<6,Forutsetninger!$B$21,Forutsetninger!$B$22)))) | T55: =IF($Z$55="",0,IF(19<$Z$55,0,IF(19-$Z$55<3,Forutsetninger!$B$20,IF(19-$Z$55<6,Forutsetninger!$B$21,Forutsetninger!$B$22)))) | U55: =IF($Z$55="",0,IF(20<$Z$55,0,IF(20-$Z$55<3,Forutsetninger!$B$20,IF(20-$Z$55<6,Forutsetninger!$B$21,Forutsetninger!$B$22)))) | V55: =IF($Z$55="",0,IF(21<$Z$55,0,IF(21-$Z$55<3,Forutsetninger!$B$20,IF(21-$Z$55<6,Forutsetninger!$B$21,Forutsetninger!$B$22)))) | W55: =IF($Z$55="",0,IF(22<$Z$55,0,IF(22-$Z$55<3,Forutsetninger!$B$20,IF(22-$Z$55<6,Forutsetninger!$B$21,Forutsetninger!$B$22)))) | X55: =IF($Z$55="",0,IF(23<$Z$55,0,IF(23-$Z$55<3,Forutsetninger!$B$20,IF(23-$Z$55<6,Forutsetninger!$B$21,Forutsetninger!$B$22)))) | Y55: =IF($Z$55="",0,IF(24<$Z$55,0,IF(24-$Z$55<3,Forutsetninger!$B$20,IF(24-$Z$55<6,Forutsetninger!$B$21,Forutsetninger!$B$22)))) | Z55: -6
A56: Megler-stol 3 (nyansatt 2027 Q1) | B56: =IF($Z$56="",0,IF(1<$Z$56,0,IF(1-$Z$56<3,Forutsetninger!$B$20,IF(1-$Z$56<6,Forutsetninger!$B$21,Forutsetninger!$B$22)))) | C56: =IF($Z$56="",0,IF(2<$Z$56,0,IF(2-$Z$56<3,Forutsetninger!$B$20,IF(2-$Z$56<6,Forutsetninger!$B$21,Forutsetninger!$B$22)))) | D56: =IF($Z$56="",0,IF(3<$Z$56,0,IF(3-$Z$56<3,Forutsetninger!$B$20,IF(3-$Z$56<6,Forutsetninger!$B$21,Forutsetninger!$B$22)))) | E56: =IF($Z$56="",0,IF(4<$Z$56,0,IF(4-$Z$56<3,Forutsetninger!$B$20,IF(4-$Z$56<6,Forutsetninger!$B$21,Forutsetninger!$B$22)))) | F56: =IF($Z$56="",0,IF(5<$Z$56,0,IF(5-$Z$56<3,Forutsetninger!$B$20,IF(5-$Z$56<6,Forutsetninger!$B$21,Forutsetninger!$B$22)))) | G56: =IF($Z$56="",0,IF(6<$Z$56,0,IF(6-$Z$56<3,Forutsetninger!$B$20,IF(6-$Z$56<6,Forutsetninger!$B$21,Forutsetninger!$B$22)))) | H56: =IF($Z$56="",0,IF(7<$Z$56,0,IF(7-$Z$56<3,Forutsetninger!$B$20,IF(7-$Z$56<6,Forutsetninger!$B$21,Forutsetninger!$B$22)))) | I56: =IF($Z$56="",0,IF(8<$Z$56,0,IF(8-$Z$56<3,Forutsetninger!$B$20,IF(8-$Z$56<6,Forutsetninger!$B$21,Forutsetninger!$B$22)))) | J56: =IF($Z$56="",0,IF(9<$Z$56,0,IF(9-$Z$56<3,Forutsetninger!$B$20,IF(9-$Z$56<6,Forutsetninger!$B$21,Forutsetninger!$B$22)))) | K56: =IF($Z$56="",0,IF(10<$Z$56,0,IF(10-$Z$56<3,Forutsetninger!$B$20,IF(10-$Z$56<6,Forutsetninger!$B$21,Forutsetninger!$B$22)))) | L56: =IF($Z$56="",0,IF(11<$Z$56,0,IF(11-$Z$56<3,Forutsetninger!$B$20,IF(11-$Z$56<6,Forutsetninger!$B$21,Forutsetninger!$B$22)))) | M56: =IF($Z$56="",0,IF(12<$Z$56,0,IF(12-$Z$56<3,Forutsetninger!$B$20,IF(12-$Z$56<6,Forutsetninger!$B$21,Forutsetninger!$B$22)))) | N56: =IF($Z$56="",0,IF(13<$Z$56,0,IF(13-$Z$56<3,Forutsetninger!$B$20,IF(13-$Z$56<6,Forutsetninger!$B$21,Forutsetninger!$B$22)))) | O56: =IF($Z$56="",0,IF(14<$Z$56,0,IF(14-$Z$56<3,Forutsetninger!$B$20,IF(14-$Z$56<6,Forutsetninger!$B$21,Forutsetninger!$B$22)))) | P56: =IF($Z$56="",0,IF(15<$Z$56,0,IF(15-$Z$56<3,Forutsetninger!$B$20,IF(15-$Z$56<6,Forutsetninger!$B$21,Forutsetninger!$B$22)))) | Q56: =IF($Z$56="",0,IF(16<$Z$56,0,IF(16-$Z$56<3,Forutsetninger!$B$20,IF(16-$Z$56<6,Forutsetninger!$B$21,Forutsetninger!$B$22)))) | R56: =IF($Z$56="",0,IF(17<$Z$56,0,IF(17-$Z$56<3,Forutsetninger!$B$20,IF(17-$Z$56<6,Forutsetninger!$B$21,Forutsetninger!$B$22)))) | S56: =IF($Z$56="",0,IF(18<$Z$56,0,IF(18-$Z$56<3,Forutsetninger!$B$20,IF(18-$Z$56<6,Forutsetninger!$B$21,Forutsetninger!$B$22)))) | T56: =IF($Z$56="",0,IF(19<$Z$56,0,IF(19-$Z$56<3,Forutsetninger!$B$20,IF(19-$Z$56<6,Forutsetninger!$B$21,Forutsetninger!$B$22)))) | U56: =IF($Z$56="",0,IF(20<$Z$56,0,IF(20-$Z$56<3,Forutsetninger!$B$20,IF(20-$Z$56<6,Forutsetninger!$B$21,Forutsetninger!$B$22)))) | V56: =IF($Z$56="",0,IF(21<$Z$56,0,IF(21-$Z$56<3,Forutsetninger!$B$20,IF(21-$Z$56<6,Forutsetninger!$B$21,Forutsetninger!$B$22)))) | W56: =IF($Z$56="",0,IF(22<$Z$56,0,IF(22-$Z$56<3,Forutsetninger!$B$20,IF(22-$Z$56<6,Forutsetninger!$B$21,Forutsetninger!$B$22)))) | X56: =IF($Z$56="",0,IF(23<$Z$56,0,IF(23-$Z$56<3,Forutsetninger!$B$20,IF(23-$Z$56<6,Forutsetninger!$B$21,Forutsetninger!$B$22)))) | Y56: =IF($Z$56="",0,IF(24<$Z$56,0,IF(24-$Z$56<3,Forutsetninger!$B$20,IF(24-$Z$56<6,Forutsetninger!$B$21,Forutsetninger!$B$22)))) | Z56: 1
A57: Megler-stol 4 (nyansatt 2027 Q2) | B57: =IF($Z$57="",0,IF(1<$Z$57,0,IF(1-$Z$57<3,Forutsetninger!$B$20,IF(1-$Z$57<6,Forutsetninger!$B$21,Forutsetninger!$B$22)))) | C57: =IF($Z$57="",0,IF(2<$Z$57,0,IF(2-$Z$57<3,Forutsetninger!$B$20,IF(2-$Z$57<6,Forutsetninger!$B$21,Forutsetninger!$B$22)))) | D57: =IF($Z$57="",0,IF(3<$Z$57,0,IF(3-$Z$57<3,Forutsetninger!$B$20,IF(3-$Z$57<6,Forutsetninger!$B$21,Forutsetninger!$B$22)))) | E57: =IF($Z$57="",0,IF(4<$Z$57,0,IF(4-$Z$57<3,Forutsetninger!$B$20,IF(4-$Z$57<6,Forutsetninger!$B$21,Forutsetninger!$B$22)))) | F57: =IF($Z$57="",0,IF(5<$Z$57,0,IF(5-$Z$57<3,Forutsetninger!$B$20,IF(5-$Z$57<6,Forutsetninger!$B$21,Forutsetninger!$B$22)))) | G57: =IF($Z$57="",0,IF(6<$Z$57,0,IF(6-$Z$57<3,Forutsetninger!$B$20,IF(6-$Z$57<6,Forutsetninger!$B$21,Forutsetninger!$B$22)))) | H57: =IF($Z$57="",0,IF(7<$Z$57,0,IF(7-$Z$57<3,Forutsetninger!$B$20,IF(7-$Z$57<6,Forutsetninger!$B$21,Forutsetninger!$B$22)))) | I57: =IF($Z$57="",0,IF(8<$Z$57,0,IF(8-$Z$57<3,Forutsetninger!$B$20,IF(8-$Z$57<6,Forutsetninger!$B$21,Forutsetninger!$B$22)))) | J57: =IF($Z$57="",0,IF(9<$Z$57,0,IF(9-$Z$57<3,Forutsetninger!$B$20,IF(9-$Z$57<6,Forutsetninger!$B$21,Forutsetninger!$B$22)))) | K57: =IF($Z$57="",0,IF(10<$Z$57,0,IF(10-$Z$57<3,Forutsetninger!$B$20,IF(10-$Z$57<6,Forutsetninger!$B$21,Forutsetninger!$B$22)))) | L57: =IF($Z$57="",0,IF(11<$Z$57,0,IF(11-$Z$57<3,Forutsetninger!$B$20,IF(11-$Z$57<6,Forutsetninger!$B$21,Forutsetninger!$B$22)))) | M57: =IF($Z$57="",0,IF(12<$Z$57,0,IF(12-$Z$57<3,Forutsetninger!$B$20,IF(12-$Z$57<6,Forutsetninger!$B$21,Forutsetninger!$B$22)))) | N57: =IF($Z$57="",0,IF(13<$Z$57,0,IF(13-$Z$57<3,Forutsetninger!$B$20,IF(13-$Z$57<6,Forutsetninger!$B$21,Forutsetninger!$B$22)))) | O57: =IF($Z$57="",0,IF(14<$Z$57,0,IF(14-$Z$57<3,Forutsetninger!$B$20,IF(14-$Z$57<6,Forutsetninger!$B$21,Forutsetninger!$B$22)))) | P57: =IF($Z$57="",0,IF(15<$Z$57,0,IF(15-$Z$57<3,Forutsetninger!$B$20,IF(15-$Z$57<6,Forutsetninger!$B$21,Forutsetninger!$B$22)))) | Q57: =IF($Z$57="",0,IF(16<$Z$57,0,IF(16-$Z$57<3,Forutsetninger!$B$20,IF(16-$Z$57<6,Forutsetninger!$B$21,Forutsetninger!$B$22)))) | R57: =IF($Z$57="",0,IF(17<$Z$57,0,IF(17-$Z$57<3,Forutsetninger!$B$20,IF(17-$Z$57<6,Forutsetninger!$B$21,Forutsetninger!$B$22)))) | S57: =IF($Z$57="",0,IF(18<$Z$57,0,IF(18-$Z$57<3,Forutsetninger!$B$20,IF(18-$Z$57<6,Forutsetninger!$B$21,Forutsetninger!$B$22)))) | T57: =IF($Z$57="",0,IF(19<$Z$57,0,IF(19-$Z$57<3,Forutsetninger!$B$20,IF(19-$Z$57<6,Forutsetninger!$B$21,Forutsetninger!$B$22)))) | U57: =IF($Z$57="",0,IF(20<$Z$57,0,IF(20-$Z$57<3,Forutsetninger!$B$20,IF(20-$Z$57<6,Forutsetninger!$B$21,Forutsetninger!$B$22)))) | V57: =IF($Z$57="",0,IF(21<$Z$57,0,IF(21-$Z$57<3,Forutsetninger!$B$20,IF(21-$Z$57<6,Forutsetninger!$B$21,Forutsetninger!$B$22)))) | W57: =IF($Z$57="",0,IF(22<$Z$57,0,IF(22-$Z$57<3,Forutsetninger!$B$20,IF(22-$Z$57<6,Forutsetninger!$B$21,Forutsetninger!$B$22)))) | X57: =IF($Z$57="",0,IF(23<$Z$57,0,IF(23-$Z$57<3,Forutsetninger!$B$20,IF(23-$Z$57<6,Forutsetninger!$B$21,Forutsetninger!$B$22)))) | Y57: =IF($Z$57="",0,IF(24<$Z$57,0,IF(24-$Z$57<3,Forutsetninger!$B$20,IF(24-$Z$57<6,Forutsetninger!$B$21,Forutsetninger!$B$22)))) | Z57: 4
A58: Megler-stol 5 (nyansatt 2027 Q3) | B58: =IF($Z$58="",0,IF(1<$Z$58,0,IF(1-$Z$58<3,Forutsetninger!$B$20,IF(1-$Z$58<6,Forutsetninger!$B$21,Forutsetninger!$B$22)))) | C58: =IF($Z$58="",0,IF(2<$Z$58,0,IF(2-$Z$58<3,Forutsetninger!$B$20,IF(2-$Z$58<6,Forutsetninger!$B$21,Forutsetninger!$B$22)))) | D58: =IF($Z$58="",0,IF(3<$Z$58,0,IF(3-$Z$58<3,Forutsetninger!$B$20,IF(3-$Z$58<6,Forutsetninger!$B$21,Forutsetninger!$B$22)))) | E58: =IF($Z$58="",0,IF(4<$Z$58,0,IF(4-$Z$58<3,Forutsetninger!$B$20,IF(4-$Z$58<6,Forutsetninger!$B$21,Forutsetninger!$B$22)))) | F58: =IF($Z$58="",0,IF(5<$Z$58,0,IF(5-$Z$58<3,Forutsetninger!$B$20,IF(5-$Z$58<6,Forutsetninger!$B$21,Forutsetninger!$B$22)))) | G58: =IF($Z$58="",0,IF(6<$Z$58,0,IF(6-$Z$58<3,Forutsetninger!$B$20,IF(6-$Z$58<6,Forutsetninger!$B$21,Forutsetninger!$B$22)))) | H58: =IF($Z$58="",0,IF(7<$Z$58,0,IF(7-$Z$58<3,Forutsetninger!$B$20,IF(7-$Z$58<6,Forutsetninger!$B$21,Forutsetninger!$B$22)))) | I58: =IF($Z$58="",0,IF(8<$Z$58,0,IF(8-$Z$58<3,Forutsetninger!$B$20,IF(8-$Z$58<6,Forutsetninger!$B$21,Forutsetninger!$B$22)))) | J58: =IF($Z$58="",0,IF(9<$Z$58,0,IF(9-$Z$58<3,Forutsetninger!$B$20,IF(9-$Z$58<6,Forutsetninger!$B$21,Forutsetninger!$B$22)))) | K58: =IF($Z$58="",0,IF(10<$Z$58,0,IF(10-$Z$58<3,Forutsetninger!$B$20,IF(10-$Z$58<6,Forutsetninger!$B$21,Forutsetninger!$B$22)))) | L58: =IF($Z$58="",0,IF(11<$Z$58,0,IF(11-$Z$58<3,Forutsetninger!$B$20,IF(11-$Z$58<6,Forutsetninger!$B$21,Forutsetninger!$B$22)))) | M58: =IF($Z$58="",0,IF(12<$Z$58,0,IF(12-$Z$58<3,Forutsetninger!$B$20,IF(12-$Z$58<6,Forutsetninger!$B$21,Forutsetninger!$B$22)))) | N58: =IF($Z$58="",0,IF(13<$Z$58,0,IF(13-$Z$58<3,Forutsetninger!$B$20,IF(13-$Z$58<6,Forutsetninger!$B$21,Forutsetninger!$B$22)))) | O58: =IF($Z$58="",0,IF(14<$Z$58,0,IF(14-$Z$58<3,Forutsetninger!$B$20,IF(14-$Z$58<6,Forutsetninger!$B$21,Forutsetninger!$B$22)))) | P58: =IF($Z$58="",0,IF(15<$Z$58,0,IF(15-$Z$58<3,Forutsetninger!$B$20,IF(15-$Z$58<6,Forutsetninger!$B$21,Forutsetninger!$B$22)))) | Q58: =IF($Z$58="",0,IF(16<$Z$58,0,IF(16-$Z$58<3,Forutsetninger!$B$20,IF(16-$Z$58<6,Forutsetninger!$B$21,Forutsetninger!$B$22)))) | R58: =IF($Z$58="",0,IF(17<$Z$58,0,IF(17-$Z$58<3,Forutsetninger!$B$20,IF(17-$Z$58<6,Forutsetninger!$B$21,Forutsetninger!$B$22)))) | S58: =IF($Z$58="",0,IF(18<$Z$58,0,IF(18-$Z$58<3,Forutsetninger!$B$20,IF(18-$Z$58<6,Forutsetninger!$B$21,Forutsetninger!$B$22)))) | T58: =IF($Z$58="",0,IF(19<$Z$58,0,IF(19-$Z$58<3,Forutsetninger!$B$20,IF(19-$Z$58<6,Forutsetninger!$B$21,Forutsetninger!$B$22)))) | U58: =IF($Z$58="",0,IF(20<$Z$58,0,IF(20-$Z$58<3,Forutsetninger!$B$20,IF(20-$Z$58<6,Forutsetninger!$B$21,Forutsetninger!$B$22)))) | V58: =IF($Z$58="",0,IF(21<$Z$58,0,IF(21-$Z$58<3,Forutsetninger!$B$20,IF(21-$Z$58<6,Forutsetninger!$B$21,Forutsetninger!$B$22)))) | W58: =IF($Z$58="",0,IF(22<$Z$58,0,IF(22-$Z$58<3,Forutsetninger!$B$20,IF(22-$Z$58<6,Forutsetninger!$B$21,Forutsetninger!$B$22)))) | X58: =IF($Z$58="",0,IF(23<$Z$58,0,IF(23-$Z$58<3,Forutsetninger!$B$20,IF(23-$Z$58<6,Forutsetninger!$B$21,Forutsetninger!$B$22)))) | Y58: =IF($Z$58="",0,IF(24<$Z$58,0,IF(24-$Z$58<3,Forutsetninger!$B$20,IF(24-$Z$58<6,Forutsetninger!$B$21,Forutsetninger!$B$22)))) | Z58: 7
A59: Megler-stol 6 (nyansatt 2028) | B59: =IF($Z$59="",0,IF(1<$Z$59,0,IF(1-$Z$59<3,Forutsetninger!$B$20,IF(1-$Z$59<6,Forutsetninger!$B$21,Forutsetninger!$B$22)))) | C59: =IF($Z$59="",0,IF(2<$Z$59,0,IF(2-$Z$59<3,Forutsetninger!$B$20,IF(2-$Z$59<6,Forutsetninger!$B$21,Forutsetninger!$B$22)))) | D59: =IF($Z$59="",0,IF(3<$Z$59,0,IF(3-$Z$59<3,Forutsetninger!$B$20,IF(3-$Z$59<6,Forutsetninger!$B$21,Forutsetninger!$B$22)))) | E59: =IF($Z$59="",0,IF(4<$Z$59,0,IF(4-$Z$59<3,Forutsetninger!$B$20,IF(4-$Z$59<6,Forutsetninger!$B$21,Forutsetninger!$B$22)))) | F59: =IF($Z$59="",0,IF(5<$Z$59,0,IF(5-$Z$59<3,Forutsetninger!$B$20,IF(5-$Z$59<6,Forutsetninger!$B$21,Forutsetninger!$B$22)))) | G59: =IF($Z$59="",0,IF(6<$Z$59,0,IF(6-$Z$59<3,Forutsetninger!$B$20,IF(6-$Z$59<6,Forutsetninger!$B$21,Forutsetninger!$B$22)))) | H59: =IF($Z$59="",0,IF(7<$Z$59,0,IF(7-$Z$59<3,Forutsetninger!$B$20,IF(7-$Z$59<6,Forutsetninger!$B$21,Forutsetninger!$B$22)))) | I59: =IF($Z$59="",0,IF(8<$Z$59,0,IF(8-$Z$59<3,Forutsetninger!$B$20,IF(8-$Z$59<6,Forutsetninger!$B$21,Forutsetninger!$B$22)))) | J59: =IF($Z$59="",0,IF(9<$Z$59,0,IF(9-$Z$59<3,Forutsetninger!$B$20,IF(9-$Z$59<6,Forutsetninger!$B$21,Forutsetninger!$B$22)))) | K59: =IF($Z$59="",0,IF(10<$Z$59,0,IF(10-$Z$59<3,Forutsetninger!$B$20,IF(10-$Z$59<6,Forutsetninger!$B$21,Forutsetninger!$B$22)))) | L59: =IF($Z$59="",0,IF(11<$Z$59,0,IF(11-$Z$59<3,Forutsetninger!$B$20,IF(11-$Z$59<6,Forutsetninger!$B$21,Forutsetninger!$B$22)))) | M59: =IF($Z$59="",0,IF(12<$Z$59,0,IF(12-$Z$59<3,Forutsetninger!$B$20,IF(12-$Z$59<6,Forutsetninger!$B$21,Forutsetninger!$B$22)))) | N59: =IF($Z$59="",0,IF(13<$Z$59,0,IF(13-$Z$59<3,Forutsetninger!$B$20,IF(13-$Z$59<6,Forutsetninger!$B$21,Forutsetninger!$B$22)))) | O59: =IF($Z$59="",0,IF(14<$Z$59,0,IF(14-$Z$59<3,Forutsetninger!$B$20,IF(14-$Z$59<6,Forutsetninger!$B$21,Forutsetninger!$B$22)))) | P59: =IF($Z$59="",0,IF(15<$Z$59,0,IF(15-$Z$59<3,Forutsetninger!$B$20,IF(15-$Z$59<6,Forutsetninger!$B$21,Forutsetninger!$B$22)))) | Q59: =IF($Z$59="",0,IF(16<$Z$59,0,IF(16-$Z$59<3,Forutsetninger!$B$20,IF(16-$Z$59<6,Forutsetninger!$B$21,Forutsetninger!$B$22)))) | R59: =IF($Z$59="",0,IF(17<$Z$59,0,IF(17-$Z$59<3,Forutsetninger!$B$20,IF(17-$Z$59<6,Forutsetninger!$B$21,Forutsetninger!$B$22)))) | S59: =IF($Z$59="",0,IF(18<$Z$59,0,IF(18-$Z$59<3,Forutsetninger!$B$20,IF(18-$Z$59<6,Forutsetninger!$B$21,Forutsetninger!$B$22)))) | T59: =IF($Z$59="",0,IF(19<$Z$59,0,IF(19-$Z$59<3,Forutsetninger!$B$20,IF(19-$Z$59<6,Forutsetninger!$B$21,Forutsetninger!$B$22)))) | U59: =IF($Z$59="",0,IF(20<$Z$59,0,IF(20-$Z$59<3,Forutsetninger!$B$20,IF(20-$Z$59<6,Forutsetninger!$B$21,Forutsetninger!$B$22)))) | V59: =IF($Z$59="",0,IF(21<$Z$59,0,IF(21-$Z$59<3,Forutsetninger!$B$20,IF(21-$Z$59<6,Forutsetninger!$B$21,Forutsetninger!$B$22)))) | W59: =IF($Z$59="",0,IF(22<$Z$59,0,IF(22-$Z$59<3,Forutsetninger!$B$20,IF(22-$Z$59<6,Forutsetninger!$B$21,Forutsetninger!$B$22)))) | X59: =IF($Z$59="",0,IF(23<$Z$59,0,IF(23-$Z$59<3,Forutsetninger!$B$20,IF(23-$Z$59<6,Forutsetninger!$B$21,Forutsetninger!$B$22)))) | Y59: =IF($Z$59="",0,IF(24<$Z$59,0,IF(24-$Z$59<3,Forutsetninger!$B$20,IF(24-$Z$59<6,Forutsetninger!$B$21,Forutsetninger!$B$22)))) | Z59: 13
A60: Megler-stol 7 (ledig) | B60: =IF($Z$60="",0,IF(1<$Z$60,0,IF(1-$Z$60<3,Forutsetninger!$B$20,IF(1-$Z$60<6,Forutsetninger!$B$21,Forutsetninger!$B$22)))) | C60: =IF($Z$60="",0,IF(2<$Z$60,0,IF(2-$Z$60<3,Forutsetninger!$B$20,IF(2-$Z$60<6,Forutsetninger!$B$21,Forutsetninger!$B$22)))) | D60: =IF($Z$60="",0,IF(3<$Z$60,0,IF(3-$Z$60<3,Forutsetninger!$B$20,IF(3-$Z$60<6,Forutsetninger!$B$21,Forutsetninger!$B$22)))) | E60: =IF($Z$60="",0,IF(4<$Z$60,0,IF(4-$Z$60<3,Forutsetninger!$B$20,IF(4-$Z$60<6,Forutsetninger!$B$21,Forutsetninger!$B$22)))) | F60: =IF($Z$60="",0,IF(5<$Z$60,0,IF(5-$Z$60<3,Forutsetninger!$B$20,IF(5-$Z$60<6,Forutsetninger!$B$21,Forutsetninger!$B$22)))) | G60: =IF($Z$60="",0,IF(6<$Z$60,0,IF(6-$Z$60<3,Forutsetninger!$B$20,IF(6-$Z$60<6,Forutsetninger!$B$21,Forutsetninger!$B$22)))) | H60: =IF($Z$60="",0,IF(7<$Z$60,0,IF(7-$Z$60<3,Forutsetninger!$B$20,IF(7-$Z$60<6,Forutsetninger!$B$21,Forutsetninger!$B$22)))) | I60: =IF($Z$60="",0,IF(8<$Z$60,0,IF(8-$Z$60<3,Forutsetninger!$B$20,IF(8-$Z$60<6,Forutsetninger!$B$21,Forutsetninger!$B$22)))) | J60: =IF($Z$60="",0,IF(9<$Z$60,0,IF(9-$Z$60<3,Forutsetninger!$B$20,IF(9-$Z$60<6,Forutsetninger!$B$21,Forutsetninger!$B$22)))) | K60: =IF($Z$60="",0,IF(10<$Z$60,0,IF(10-$Z$60<3,Forutsetninger!$B$20,IF(10-$Z$60<6,Forutsetninger!$B$21,Forutsetninger!$B$22)))) | L60: =IF($Z$60="",0,IF(11<$Z$60,0,IF(11-$Z$60<3,Forutsetninger!$B$20,IF(11-$Z$60<6,Forutsetninger!$B$21,Forutsetninger!$B$22)))) | M60: =IF($Z$60="",0,IF(12<$Z$60,0,IF(12-$Z$60<3,Forutsetninger!$B$20,IF(12-$Z$60<6,Forutsetninger!$B$21,Forutsetninger!$B$22)))) | N60: =IF($Z$60="",0,IF(13<$Z$60,0,IF(13-$Z$60<3,Forutsetninger!$B$20,IF(13-$Z$60<6,Forutsetninger!$B$21,Forutsetninger!$B$22)))) | O60: =IF($Z$60="",0,IF(14<$Z$60,0,IF(14-$Z$60<3,Forutsetninger!$B$20,IF(14-$Z$60<6,Forutsetninger!$B$21,Forutsetninger!$B$22)))) | P60: =IF($Z$60="",0,IF(15<$Z$60,0,IF(15-$Z$60<3,Forutsetninger!$B$20,IF(15-$Z$60<6,Forutsetninger!$B$21,Forutsetninger!$B$22)))) | Q60: =IF($Z$60="",0,IF(16<$Z$60,0,IF(16-$Z$60<3,Forutsetninger!$B$20,IF(16-$Z$60<6,Forutsetninger!$B$21,Forutsetninger!$B$22)))) | R60: =IF($Z$60="",0,IF(17<$Z$60,0,IF(17-$Z$60<3,Forutsetninger!$B$20,IF(17-$Z$60<6,Forutsetninger!$B$21,Forutsetninger!$B$22)))) | S60: =IF($Z$60="",0,IF(18<$Z$60,0,IF(18-$Z$60<3,Forutsetninger!$B$20,IF(18-$Z$60<6,Forutsetninger!$B$21,Forutsetninger!$B$22)))) | T60: =IF($Z$60="",0,IF(19<$Z$60,0,IF(19-$Z$60<3,Forutsetninger!$B$20,IF(19-$Z$60<6,Forutsetninger!$B$21,Forutsetninger!$B$22)))) | U60: =IF($Z$60="",0,IF(20<$Z$60,0,IF(20-$Z$60<3,Forutsetninger!$B$20,IF(20-$Z$60<6,Forutsetninger!$B$21,Forutsetninger!$B$22)))) | V60: =IF($Z$60="",0,IF(21<$Z$60,0,IF(21-$Z$60<3,Forutsetninger!$B$20,IF(21-$Z$60<6,Forutsetninger!$B$21,Forutsetninger!$B$22)))) | W60: =IF($Z$60="",0,IF(22<$Z$60,0,IF(22-$Z$60<3,Forutsetninger!$B$20,IF(22-$Z$60<6,Forutsetninger!$B$21,Forutsetninger!$B$22)))) | X60: =IF($Z$60="",0,IF(23<$Z$60,0,IF(23-$Z$60<3,Forutsetninger!$B$20,IF(23-$Z$60<6,Forutsetninger!$B$21,Forutsetninger!$B$22)))) | Y60: =IF($Z$60="",0,IF(24<$Z$60,0,IF(24-$Z$60<3,Forutsetninger!$B$20,IF(24-$Z$60<6,Forutsetninger!$B$21,Forutsetninger!$B$22))))
A61: Megler-stol 8 (ledig) | B61: =IF($Z$61="",0,IF(1<$Z$61,0,IF(1-$Z$61<3,Forutsetninger!$B$20,IF(1-$Z$61<6,Forutsetninger!$B$21,Forutsetninger!$B$22)))) | C61: =IF($Z$61="",0,IF(2<$Z$61,0,IF(2-$Z$61<3,Forutsetninger!$B$20,IF(2-$Z$61<6,Forutsetninger!$B$21,Forutsetninger!$B$22)))) | D61: =IF($Z$61="",0,IF(3<$Z$61,0,IF(3-$Z$61<3,Forutsetninger!$B$20,IF(3-$Z$61<6,Forutsetninger!$B$21,Forutsetninger!$B$22)))) | E61: =IF($Z$61="",0,IF(4<$Z$61,0,IF(4-$Z$61<3,Forutsetninger!$B$20,IF(4-$Z$61<6,Forutsetninger!$B$21,Forutsetninger!$B$22)))) | F61: =IF($Z$61="",0,IF(5<$Z$61,0,IF(5-$Z$61<3,Forutsetninger!$B$20,IF(5-$Z$61<6,Forutsetninger!$B$21,Forutsetninger!$B$22)))) | G61: =IF($Z$61="",0,IF(6<$Z$61,0,IF(6-$Z$61<3,Forutsetninger!$B$20,IF(6-$Z$61<6,Forutsetninger!$B$21,Forutsetninger!$B$22)))) | H61: =IF($Z$61="",0,IF(7<$Z$61,0,IF(7-$Z$61<3,Forutsetninger!$B$20,IF(7-$Z$61<6,Forutsetninger!$B$21,Forutsetninger!$B$22)))) | I61: =IF($Z$61="",0,IF(8<$Z$61,0,IF(8-$Z$61<3,Forutsetninger!$B$20,IF(8-$Z$61<6,Forutsetninger!$B$21,Forutsetninger!$B$22)))) | J61: =IF($Z$61="",0,IF(9<$Z$61,0,IF(9-$Z$61<3,Forutsetninger!$B$20,IF(9-$Z$61<6,Forutsetninger!$B$21,Forutsetninger!$B$22)))) | K61: =IF($Z$61="",0,IF(10<$Z$61,0,IF(10-$Z$61<3,Forutsetninger!$B$20,IF(10-$Z$61<6,Forutsetninger!$B$21,Forutsetninger!$B$22)))) | L61: =IF($Z$61="",0,IF(11<$Z$61,0,IF(11-$Z$61<3,Forutsetninger!$B$20,IF(11-$Z$61<6,Forutsetninger!$B$21,Forutsetninger!$B$22)))) | M61: =IF($Z$61="",0,IF(12<$Z$61,0,IF(12-$Z$61<3,Forutsetninger!$B$20,IF(12-$Z$61<6,Forutsetninger!$B$21,Forutsetninger!$B$22)))) | N61: =IF($Z$61="",0,IF(13<$Z$61,0,IF(13-$Z$61<3,Forutsetninger!$B$20,IF(13-$Z$61<6,Forutsetninger!$B$21,Forutsetninger!$B$22)))) | O61: =IF($Z$61="",0,IF(14<$Z$61,0,IF(14-$Z$61<3,Forutsetninger!$B$20,IF(14-$Z$61<6,Forutsetninger!$B$21,Forutsetninger!$B$22)))) | P61: =IF($Z$61="",0,IF(15<$Z$61,0,IF(15-$Z$61<3,Forutsetninger!$B$20,IF(15-$Z$61<6,Forutsetninger!$B$21,Forutsetninger!$B$22)))) | Q61: =IF($Z$61="",0,IF(16<$Z$61,0,IF(16-$Z$61<3,Forutsetninger!$B$20,IF(16-$Z$61<6,Forutsetninger!$B$21,Forutsetninger!$B$22)))) | R61: =IF($Z$61="",0,IF(17<$Z$61,0,IF(17-$Z$61<3,Forutsetninger!$B$20,IF(17-$Z$61<6,Forutsetninger!$B$21,Forutsetninger!$B$22)))) | S61: =IF($Z$61="",0,IF(18<$Z$61,0,IF(18-$Z$61<3,Forutsetninger!$B$20,IF(18-$Z$61<6,Forutsetninger!$B$21,Forutsetninger!$B$22)))) | T61: =IF($Z$61="",0,IF(19<$Z$61,0,IF(19-$Z$61<3,Forutsetninger!$B$20,IF(19-$Z$61<6,Forutsetninger!$B$21,Forutsetninger!$B$22)))) | U61: =IF($Z$61="",0,IF(20<$Z$61,0,IF(20-$Z$61<3,Forutsetninger!$B$20,IF(20-$Z$61<6,Forutsetninger!$B$21,Forutsetninger!$B$22)))) | V61: =IF($Z$61="",0,IF(21<$Z$61,0,IF(21-$Z$61<3,Forutsetninger!$B$20,IF(21-$Z$61<6,Forutsetninger!$B$21,Forutsetninger!$B$22)))) | W61: =IF($Z$61="",0,IF(22<$Z$61,0,IF(22-$Z$61<3,Forutsetninger!$B$20,IF(22-$Z$61<6,Forutsetninger!$B$21,Forutsetninger!$B$22)))) | X61: =IF($Z$61="",0,IF(23<$Z$61,0,IF(23-$Z$61<3,Forutsetninger!$B$20,IF(23-$Z$61<6,Forutsetninger!$B$21,Forutsetninger!$B$22)))) | Y61: =IF($Z$61="",0,IF(24<$Z$61,0,IF(24-$Z$61<3,Forutsetninger!$B$20,IF(24-$Z$61<6,Forutsetninger!$B$21,Forutsetninger!$B$22))))
A62: Producing megler-FTE (sum stoler) | B62: =B54+B55+B56+B57+B58+B59+B60+B61 | C62: =C54+C55+C56+C57+C58+C59+C60+C61 | D62: =D54+D55+D56+D57+D58+D59+D60+D61 | E62: =E54+E55+E56+E57+E58+E59+E60+E61 | F62: =F54+F55+F56+F57+F58+F59+F60+F61 | G62: =G54+G55+G56+G57+G58+G59+G60+G61 | H62: =H54+H55+H56+H57+H58+H59+H60+H61 | I62: =I54+I55+I56+I57+I58+I59+I60+I61 | ... Y62: =Y54+Y55+Y56+Y57+Y58+Y59+Y60+Y61 | Z62: =AVERAGE(B62:M62) | AA62: =AVERAGE(N62:Y62)
A63: Bemannede stoler v/månedsslutt (u/Sindre) | B63: =SUMPRODUCT(($Z$54:$Z$61<>"")*($Z$54:$Z$61<=1)) | C63: =SUMPRODUCT(($Z$54:$Z$61<>"")*($Z$54:$Z$61<=2)) | D63: =SUMPRODUCT(($Z$54:$Z$61<>"")*($Z$54:$Z$61<=3)) | E63: =SUMPRODUCT(($Z$54:$Z$61<>"")*($Z$54:$Z$61<=4)) | F63: =SUMPRODUCT(($Z$54:$Z$61<>"")*($Z$54:$Z$61<=5)) | G63: =SUMPRODUCT(($Z$54:$Z$61<>"")*($Z$54:$Z$61<=6)) | H63: =SUMPRODUCT(($Z$54:$Z$61<>"")*($Z$54:$Z$61<=7)) | I63: =SUMPRODUCT(($Z$54:$Z$61<>"")*($Z$54:$Z$61<=8)) | J63: =SUMPRODUCT(($Z$54:$Z$61<>"")*($Z$54:$Z$61<=9)) | K63: =SUMPRODUCT(($Z$54:$Z$61<>"")*($Z$54:$Z$61<=10)) | L63: =SUMPRODUCT(($Z$54:$Z$61<>"")*($Z$54:$Z$61<=11)) | M63: =SUMPRODUCT(($Z$54:$Z$61<>"")*($Z$54:$Z$61<=12)) | N63: =SUMPRODUCT(($Z$54:$Z$61<>"")*($Z$54:$Z$61<=13)) | O63: =SUMPRODUCT(($Z$54:$Z$61<>"")*($Z$54:$Z$61<=14)) | P63: =SUMPRODUCT(($Z$54:$Z$61<>"")*($Z$54:$Z$61<=15)) | Q63: =SUMPRODUCT(($Z$54:$Z$61<>"")*($Z$54:$Z$61<=16)) | R63: =SUMPRODUCT(($Z$54:$Z$61<>"")*($Z$54:$Z$61<=17)) | S63: =SUMPRODUCT(($Z$54:$Z$61<>"")*($Z$54:$Z$61<=18)) | T63: =SUMPRODUCT(($Z$54:$Z$61<>"")*($Z$54:$Z$61<=19)) | U63: =SUMPRODUCT(($Z$54:$Z$61<>"")*($Z$54:$Z$61<=20)) | V63: =SUMPRODUCT(($Z$54:$Z$61<>"")*($Z$54:$Z$61<=21)) | W63: =SUMPRODUCT(($Z$54:$Z$61<>"")*($Z$54:$Z$61<=22)) | X63: =SUMPRODUCT(($Z$54:$Z$61<>"")*($Z$54:$Z$61<=23)) | Y63: =SUMPRODUCT(($Z$54:$Z$61<>"")*($Z$54:$Z$61<=24)) | Z63: =M63 | AA63: =Y63
A65: E. OMSETNING BOKFØRT (i salgsmåneden) — ex mva
A66: Megler-omsetning bokført | B66: =B62*Forutsetninger!$B$13/12*IF($B$32=1,$B$48*12,1) | C66: =C62*Forutsetninger!$B$13/12*IF($B$32=1,$C$48*12,1) | D66: =D62*Forutsetninger!$B$13/12*IF($B$32=1,$D$48*12,1) | E66: =E62*Forutsetninger!$B$13/12*IF($B$32=1,$E$48*12,1) | F66: =F62*Forutsetninger!$B$13/12*IF($B$32=1,$F$48*12,1) | G66: =G62*Forutsetninger!$B$13/12*IF($B$32=1,$G$48*12,1) | H66: =H62*Forutsetninger!$B$13/12*IF($B$32=1,$H$48*12,1) | I66: =I62*Forutsetninger!$B$13/12*IF($B$32=1,$I$48*12,1) | J66: =J62*Forutsetninger!$B$13/12*IF($B$32=1,$J$48*12,1) | K66: =K62*Forutsetninger!$B$13/12*IF($B$32=1,$K$48*12,1) | L66: =L62*Forutsetninger!$B$13/12*IF($B$32=1,$L$48*12,1) | M66: =M62*Forutsetninger!$B$13/12*IF($B$32=1,$M$48*12,1) | N66: =N62*Forutsetninger!$B$13/12*IF($B$32=1,$B$48*12,1) | O66: =O62*Forutsetninger!$B$13/12*IF($B$32=1,$C$48*12,1) | P66: =P62*Forutsetninger!$B$13/12*IF($B$32=1,$D$48*12,1) | Q66: =Q62*Forutsetninger!$B$13/12*IF($B$32=1,$E$48*12,1) | R66: =R62*Forutsetninger!$B$13/12*IF($B$32=1,$F$48*12,1) | S66: =S62*Forutsetninger!$B$13/12*IF($B$32=1,$G$48*12,1) | T66: =T62*Forutsetninger!$B$13/12*IF($B$32=1,$H$48*12,1) | U66: =U62*Forutsetninger!$B$13/12*IF($B$32=1,$I$48*12,1) | V66: =V62*Forutsetninger!$B$13/12*IF($B$32=1,$J$48*12,1) | W66: =W62*Forutsetninger!$B$13/12*IF($B$32=1,$K$48*12,1) | X66: =X62*Forutsetninger!$B$13/12*IF($B$32=1,$L$48*12,1) | Y66: =Y62*Forutsetninger!$B$13/12*IF($B$32=1,$M$48*12,1) | Z66: =SUM(B66:M66) | AA66: =SUM(N66:Y66)
A67: Sindre-omsetning bokført | B67: =Forutsetninger!$B$14/12*IF($B$32=1,$B$48*12,1) | C67: =Forutsetninger!$B$14/12*IF($B$32=1,$C$48*12,1) | D67: =Forutsetninger!$B$14/12*IF($B$32=1,$D$48*12,1) | E67: =Forutsetninger!$B$14/12*IF($B$32=1,$E$48*12,1) | F67: =Forutsetninger!$B$14/12*IF($B$32=1,$F$48*12,1) | G67: =Forutsetninger!$B$14/12*IF($B$32=1,$G$48*12,1) | H67: =Forutsetninger!$B$14/12*IF($B$32=1,$H$48*12,1) | I67: =Forutsetninger!$B$14/12*IF($B$32=1,$I$48*12,1) | J67: =Forutsetninger!$B$14/12*IF($B$32=1,$J$48*12,1) | K67: =Forutsetninger!$B$14/12*IF($B$32=1,$K$48*12,1) | L67: =Forutsetninger!$B$14/12*IF($B$32=1,$L$48*12,1) | M67: =Forutsetninger!$B$14/12*IF($B$32=1,$M$48*12,1) | N67: =Forutsetninger!$B$14/12*IF($B$32=1,$B$48*12,1) | O67: =Forutsetninger!$B$14/12*IF($B$32=1,$C$48*12,1) | P67: =Forutsetninger!$B$14/12*IF($B$32=1,$D$48*12,1) | Q67: =Forutsetninger!$B$14/12*IF($B$32=1,$E$48*12,1) | R67: =Forutsetninger!$B$14/12*IF($B$32=1,$F$48*12,1) | S67: =Forutsetninger!$B$14/12*IF($B$32=1,$G$48*12,1) | T67: =Forutsetninger!$B$14/12*IF($B$32=1,$H$48*12,1) | U67: =Forutsetninger!$B$14/12*IF($B$32=1,$I$48*12,1) | V67: =Forutsetninger!$B$14/12*IF($B$32=1,$J$48*12,1) | W67: =Forutsetninger!$B$14/12*IF($B$32=1,$K$48*12,1) | X67: =Forutsetninger!$B$14/12*IF($B$32=1,$L$48*12,1) | Y67: =Forutsetninger!$B$14/12*IF($B$32=1,$M$48*12,1) | Z67: =SUM(B67:M67) | AA67: =SUM(N67:Y67)
A68: Sum provisjon bokført (ex mva) | B68: =B66+B67 | C68: =C66+C67 | D68: =D66+D67 | E68: =E66+E67 | F68: =F66+F67 | G68: =G66+G67 | H68: =H66+H67 | I68: =I66+I67 | ... Y68: =Y66+Y67 | Z68: =SUM(B68:M68) | AA68: =SUM(N68:Y68)
A69: Båter solgt (informativ) | B69: =B68/Forutsetninger!$B$5 | C69: =C68/Forutsetninger!$B$5 | D69: =D68/Forutsetninger!$B$5 | E69: =E68/Forutsetninger!$B$5 | F69: =F68/Forutsetninger!$B$5 | G69: =G68/Forutsetninger!$B$5 | H69: =H68/Forutsetninger!$B$5 | I69: =I68/Forutsetninger!$B$5 | ... Y69: =Y68/Forutsetninger!$B$5 | Z69: =SUM(B69:M69) | AA69: =SUM(N69:Y69)
A70: Overheng: provisjon fra båter solgt okt–des 2026 som innbetales i 2027 (ANSLAG). Uten dette blir jan–mar 2027 kunstig tørt (salg tidlig i 2027 betales ~89 dg senere).
A71: Bokført provisjon okt / nov / des 2026 (ANSLAG) | B71: 170000 | C71: 225000 | D71: 155000 | E71: ← okt / nov / des 2026
A73: F. INNBETALING (fra kunder, inkl. mva) = bokført provisjon × 1,25 × betalingsprofil
A74: Innbetalt fra kunder (provisjon inkl. mva) | B74: =B68*(1+$B$35)*$B$43+$D$71*(1+$B$35)*$C$43+$C$71*(1+$B$35)*$D$43+$B$71*(1+$B$35)*$E$43 | C74: =C68*(1+$B$35)*$B$43+B68*(1+$B$35)*$C$43+$D$71*(1+$B$35)*$D$43+$C$71*(1+$B$35)*$E$43+$B$71*(1+$B$35)*$F$43 | D74: =D68*(1+$B$35)*$B$43+C68*(1+$B$35)*$C$43+B68*(1+$B$35)*$D$43+$D$71*(1+$B$35)*$E$43+$C$71*(1+$B$35)*$F$43 | E74: =E68*(1+$B$35)*$B$43+D68*(1+$B$35)*$C$43+C68*(1+$B$35)*$D$43+B68*(1+$B$35)*$E$43+$D$71*(1+$B$35)*$F$43 | F74: =F68*(1+$B$35)*$B$43+E68*(1+$B$35)*$C$43+D68*(1+$B$35)*$D$43+C68*(1+$B$35)*$E$43+B68*(1+$B$35)*$F$43 | G74: =G68*(1+$B$35)*$B$43+F68*(1+$B$35)*$C$43+E68*(1+$B$35)*$D$43+D68*(1+$B$35)*$E$43+C68*(1+$B$35)*$F$43 | H74: =H68*(1+$B$35)*$B$43+G68*(1+$B$35)*$C$43+F68*(1+$B$35)*$D$43+E68*(1+$B$35)*$E$43+D68*(1+$B$35)*$F$43 | I74: =I68*(1+$B$35)*$B$43+H68*(1+$B$35)*$C$43+G68*(1+$B$35)*$D$43+F68*(1+$B$35)*$E$43+E68*(1+$B$35)*$F$43 | J74: =J68*(1+$B$35)*$B$43+I68*(1+$B$35)*$C$43+H68*(1+$B$35)*$D$43+G68*(1+$B$35)*$E$43+F68*(1+$B$35)*$F$43 | K74: =K68*(1+$B$35)*$B$43+J68*(1+$B$35)*$C$43+I68*(1+$B$35)*$D$43+H68*(1+$B$35)*$E$43+G68*(1+$B$35)*$F$43 | L74: =L68*(1+$B$35)*$B$43+K68*(1+$B$35)*$C$43+J68*(1+$B$35)*$D$43+I68*(1+$B$35)*$E$43+H68*(1+$B$35)*$F$43 | M74: =M68*(1+$B$35)*$B$43+L68*(1+$B$35)*$C$43+K68*(1+$B$35)*$D$43+J68*(1+$B$35)*$E$43+I68*(1+$B$35)*$F$43 | ... Y74: =Y68*(1+$B$35)*$B$43+X68*(1+$B$35)*$C$43+W68*(1+$B$35)*$D$43+V68*(1+$B$35)*$E$43+U68*(1+$B$35)*$F$43 | Z74: =SUM(B74:M74) | AA74: =SUM(N74:Y74)
A75: Kunden betaler provisjon + 25 % mva. HoY holder mva-en til terminoppgjøret (rad under i G). Ex mva-provisjonen er «Sum provisjon bokført» i blokk E.
A77: G. UTBETALINGER
A78: Meglerutbetaling (55 % av megler-oms) | B78: =IF(1-$B$34>=1,INDEX(B66:Y66,1,1-$B$34),0)*Forutsetninger!$B$34 | C78: =IF(2-$B$34>=1,INDEX(B66:Y66,1,2-$B$34),0)*Forutsetninger!$B$34 | D78: =IF(3-$B$34>=1,INDEX(B66:Y66,1,3-$B$34),0)*Forutsetninger!$B$34 | E78: =IF(4-$B$34>=1,INDEX(B66:Y66,1,4-$B$34),0)*Forutsetninger!$B$34 | F78: =IF(5-$B$34>=1,INDEX(B66:Y66,1,5-$B$34),0)*Forutsetninger!$B$34 | G78: =IF(6-$B$34>=1,INDEX(B66:Y66,1,6-$B$34),0)*Forutsetninger!$B$34 | H78: =IF(7-$B$34>=1,INDEX(B66:Y66,1,7-$B$34),0)*Forutsetninger!$B$34 | I78: =IF(8-$B$34>=1,INDEX(B66:Y66,1,8-$B$34),0)*Forutsetninger!$B$34 | J78: =IF(9-$B$34>=1,INDEX(B66:Y66,1,9-$B$34),0)*Forutsetninger!$B$34 | K78: =IF(10-$B$34>=1,INDEX(B66:Y66,1,10-$B$34),0)*Forutsetninger!$B$34 | L78: =IF(11-$B$34>=1,INDEX(B66:Y66,1,11-$B$34),0)*Forutsetninger!$B$34 | M78: =IF(12-$B$34>=1,INDEX(B66:Y66,1,12-$B$34),0)*Forutsetninger!$B$34 | N78: =IF(13-$B$34>=1,INDEX(B66:Y66,1,13-$B$34),0)*Forutsetninger!$B$34 | O78: =IF(14-$B$34>=1,INDEX(B66:Y66,1,14-$B$34),0)*Forutsetninger!$B$34 | P78: =IF(15-$B$34>=1,INDEX(B66:Y66,1,15-$B$34),0)*Forutsetninger!$B$34 | Q78: =IF(16-$B$34>=1,INDEX(B66:Y66,1,16-$B$34),0)*Forutsetninger!$B$34 | R78: =IF(17-$B$34>=1,INDEX(B66:Y66,1,17-$B$34),0)*Forutsetninger!$B$34 | S78: =IF(18-$B$34>=1,INDEX(B66:Y66,1,18-$B$34),0)*Forutsetninger!$B$34 | T78: =IF(19-$B$34>=1,INDEX(B66:Y66,1,19-$B$34),0)*Forutsetninger!$B$34 | U78: =IF(20-$B$34>=1,INDEX(B66:Y66,1,20-$B$34),0)*Forutsetninger!$B$34 | V78: =IF(21-$B$34>=1,INDEX(B66:Y66,1,21-$B$34),0)*Forutsetninger!$B$34 | W78: =IF(22-$B$34>=1,INDEX(B66:Y66,1,22-$B$34),0)*Forutsetninger!$B$34 | X78: =IF(23-$B$34>=1,INDEX(B66:Y66,1,23-$B$34),0)*Forutsetninger!$B$34 | Y78: =IF(24-$B$34>=1,INDEX(B66:Y66,1,24-$B$34),0)*Forutsetninger!$B$34 | Z78: =SUM(B78:M78) | AA78: =SUM(N78:Y78)
A79: Sindre-lønn (7,1G, loaded) | B79: =MIN(Forutsetninger!$B$37*Forutsetninger!$B$14,Forutsetninger!$B$36)*Forutsetninger!$B$38/12 | C79: =MIN(Forutsetninger!$B$37*Forutsetninger!$B$14,Forutsetninger!$B$36)*Forutsetninger!$B$38/12 | D79: =MIN(Forutsetninger!$B$37*Forutsetninger!$B$14,Forutsetninger!$B$36)*Forutsetninger!$B$38/12 | E79: =MIN(Forutsetninger!$B$37*Forutsetninger!$B$14,Forutsetninger!$B$36)*Forutsetninger!$B$38/12 | F79: =MIN(Forutsetninger!$B$37*Forutsetninger!$B$14,Forutsetninger!$B$36)*Forutsetninger!$B$38/12 | G79: =MIN(Forutsetninger!$B$37*Forutsetninger!$B$14,Forutsetninger!$B$36)*Forutsetninger!$B$38/12 | H79: =MIN(Forutsetninger!$B$37*Forutsetninger!$B$14,Forutsetninger!$B$36)*Forutsetninger!$B$38/12 | I79: =MIN(Forutsetninger!$B$37*Forutsetninger!$B$14,Forutsetninger!$B$36)*Forutsetninger!$B$38/12 | ... Y79: =MIN(Forutsetninger!$B$37*Forutsetninger!$B$14,Forutsetninger!$B$36)*Forutsetninger!$B$38/12 | Z79: =SUM(B79:M79) | AA79: =SUM(N79:Y79)
A80: Kostbase (trinnvis) per måned | B80: =IF(1<=12,$Z$80,$AA$80)/12 | C80: =IF(2<=12,$Z$80,$AA$80)/12 | D80: =IF(3<=12,$Z$80,$AA$80)/12 | E80: =IF(4<=12,$Z$80,$AA$80)/12 | F80: =IF(5<=12,$Z$80,$AA$80)/12 | G80: =IF(6<=12,$Z$80,$AA$80)/12 | H80: =IF(7<=12,$Z$80,$AA$80)/12 | I80: =IF(8<=12,$Z$80,$AA$80)/12 | J80: =IF(9<=12,$Z$80,$AA$80)/12 | K80: =IF(10<=12,$Z$80,$AA$80)/12 | L80: =IF(11<=12,$Z$80,$AA$80)/12 | M80: =IF(12<=12,$Z$80,$AA$80)/12 | N80: =IF(13<=12,$Z$80,$AA$80)/12 | O80: =IF(14<=12,$Z$80,$AA$80)/12 | P80: =IF(15<=12,$Z$80,$AA$80)/12 | Q80: =IF(16<=12,$Z$80,$AA$80)/12 | R80: =IF(17<=12,$Z$80,$AA$80)/12 | S80: =IF(18<=12,$Z$80,$AA$80)/12 | T80: =IF(19<=12,$Z$80,$AA$80)/12 | U80: =IF(20<=12,$Z$80,$AA$80)/12 | V80: =IF(21<=12,$Z$80,$AA$80)/12 | W80: =IF(22<=12,$Z$80,$AA$80)/12 | X80: =IF(23<=12,$Z$80,$AA$80)/12 | Y80: =IF(24<=12,$Z$80,$AA$80)/12 | Z80: =Forutsetninger!$B$25+Forutsetninger!$B$26*MAX(0,Z63-2)+IF(Z63>=5,Forutsetninger!$B$29,0)+IF(Z63>=6,Forutsetninger!$B$28,0)+IF(Z63>=8,Forutsetninger!$B$30,0) | AA80: =Forutsetninger!$B$25+Forutsetninger!$B$26*MAX(0,AA63-2)+IF(AA63>=5,Forutsetninger!$B$29,0)+IF(AA63>=6,Forutsetninger!$B$28,0)+IF(AA63>=8,Forutsetninger!$B$30,0)
A81: Onboarding nyansatt (engang) | B81: =SUMPRODUCT(($Z$54:$Z$61=1)*1)*Forutsetninger!$B$27 | C81: =SUMPRODUCT(($Z$54:$Z$61=2)*1)*Forutsetninger!$B$27 | D81: =SUMPRODUCT(($Z$54:$Z$61=3)*1)*Forutsetninger!$B$27 | E81: =SUMPRODUCT(($Z$54:$Z$61=4)*1)*Forutsetninger!$B$27 | F81: =SUMPRODUCT(($Z$54:$Z$61=5)*1)*Forutsetninger!$B$27 | G81: =SUMPRODUCT(($Z$54:$Z$61=6)*1)*Forutsetninger!$B$27 | H81: =SUMPRODUCT(($Z$54:$Z$61=7)*1)*Forutsetninger!$B$27 | I81: =SUMPRODUCT(($Z$54:$Z$61=8)*1)*Forutsetninger!$B$27 | J81: =SUMPRODUCT(($Z$54:$Z$61=9)*1)*Forutsetninger!$B$27 | K81: =SUMPRODUCT(($Z$54:$Z$61=10)*1)*Forutsetninger!$B$27 | L81: =SUMPRODUCT(($Z$54:$Z$61=11)*1)*Forutsetninger!$B$27 | M81: =SUMPRODUCT(($Z$54:$Z$61=12)*1)*Forutsetninger!$B$27 | N81: =SUMPRODUCT(($Z$54:$Z$61=13)*1)*Forutsetninger!$B$27 | O81: =SUMPRODUCT(($Z$54:$Z$61=14)*1)*Forutsetninger!$B$27 | P81: =SUMPRODUCT(($Z$54:$Z$61=15)*1)*Forutsetninger!$B$27 | Q81: =SUMPRODUCT(($Z$54:$Z$61=16)*1)*Forutsetninger!$B$27 | R81: =SUMPRODUCT(($Z$54:$Z$61=17)*1)*Forutsetninger!$B$27 | S81: =SUMPRODUCT(($Z$54:$Z$61=18)*1)*Forutsetninger!$B$27 | T81: =SUMPRODUCT(($Z$54:$Z$61=19)*1)*Forutsetninger!$B$27 | U81: =SUMPRODUCT(($Z$54:$Z$61=20)*1)*Forutsetninger!$B$27 | V81: =SUMPRODUCT(($Z$54:$Z$61=21)*1)*Forutsetninger!$B$27 | W81: =SUMPRODUCT(($Z$54:$Z$61=22)*1)*Forutsetninger!$B$27 | X81: =SUMPRODUCT(($Z$54:$Z$61=23)*1)*Forutsetninger!$B$27 | Y81: =SUMPRODUCT(($Z$54:$Z$61=24)*1)*Forutsetninger!$B$27 | Z81: =SUM(B81:M81) | AA81: =SUM(N81:Y81)
A82: Markedskost (per signert oppdrag) | B82: =INDEX(B68:Y68,1,MIN(24,1+$B$33))/Forutsetninger!$B$5*Forutsetninger!$B$41*Forutsetninger!$B$31 | C82: =INDEX(B68:Y68,1,MIN(24,2+$B$33))/Forutsetninger!$B$5*Forutsetninger!$B$41*Forutsetninger!$B$31 | D82: =INDEX(B68:Y68,1,MIN(24,3+$B$33))/Forutsetninger!$B$5*Forutsetninger!$B$41*Forutsetninger!$B$31 | E82: =INDEX(B68:Y68,1,MIN(24,4+$B$33))/Forutsetninger!$B$5*Forutsetninger!$B$41*Forutsetninger!$B$31 | F82: =INDEX(B68:Y68,1,MIN(24,5+$B$33))/Forutsetninger!$B$5*Forutsetninger!$B$41*Forutsetninger!$B$31 | G82: =INDEX(B68:Y68,1,MIN(24,6+$B$33))/Forutsetninger!$B$5*Forutsetninger!$B$41*Forutsetninger!$B$31 | H82: =INDEX(B68:Y68,1,MIN(24,7+$B$33))/Forutsetninger!$B$5*Forutsetninger!$B$41*Forutsetninger!$B$31 | I82: =INDEX(B68:Y68,1,MIN(24,8+$B$33))/Forutsetninger!$B$5*Forutsetninger!$B$41*Forutsetninger!$B$31 | J82: =INDEX(B68:Y68,1,MIN(24,9+$B$33))/Forutsetninger!$B$5*Forutsetninger!$B$41*Forutsetninger!$B$31 | K82: =INDEX(B68:Y68,1,MIN(24,10+$B$33))/Forutsetninger!$B$5*Forutsetninger!$B$41*Forutsetninger!$B$31 | L82: =INDEX(B68:Y68,1,MIN(24,11+$B$33))/Forutsetninger!$B$5*Forutsetninger!$B$41*Forutsetninger!$B$31 | M82: =INDEX(B68:Y68,1,MIN(24,12+$B$33))/Forutsetninger!$B$5*Forutsetninger!$B$41*Forutsetninger!$B$31 | N82: =INDEX(B68:Y68,1,MIN(24,13+$B$33))/Forutsetninger!$B$5*Forutsetninger!$B$41*Forutsetninger!$B$31 | O82: =INDEX(B68:Y68,1,MIN(24,14+$B$33))/Forutsetninger!$B$5*Forutsetninger!$B$41*Forutsetninger!$B$31 | P82: =INDEX(B68:Y68,1,MIN(24,15+$B$33))/Forutsetninger!$B$5*Forutsetninger!$B$41*Forutsetninger!$B$31 | Q82: =INDEX(B68:Y68,1,MIN(24,16+$B$33))/Forutsetninger!$B$5*Forutsetninger!$B$41*Forutsetninger!$B$31 | R82: =INDEX(B68:Y68,1,MIN(24,17+$B$33))/Forutsetninger!$B$5*Forutsetninger!$B$41*Forutsetninger!$B$31 | S82: =INDEX(B68:Y68,1,MIN(24,18+$B$33))/Forutsetninger!$B$5*Forutsetninger!$B$41*Forutsetninger!$B$31 | T82: =INDEX(B68:Y68,1,MIN(24,19+$B$33))/Forutsetninger!$B$5*Forutsetninger!$B$41*Forutsetninger!$B$31 | U82: =INDEX(B68:Y68,1,MIN(24,20+$B$33))/Forutsetninger!$B$5*Forutsetninger!$B$41*Forutsetninger!$B$31 | V82: =INDEX(B68:Y68,1,MIN(24,21+$B$33))/Forutsetninger!$B$5*Forutsetninger!$B$41*Forutsetninger!$B$31 | W82: =INDEX(B68:Y68,1,MIN(24,22+$B$33))/Forutsetninger!$B$5*Forutsetninger!$B$41*Forutsetninger!$B$31 | X82: =INDEX(B68:Y68,1,MIN(24,23+$B$33))/Forutsetninger!$B$5*Forutsetninger!$B$41*Forutsetninger!$B$31 | Y82: =INDEX(B68:Y68,1,MIN(24,24+$B$33))/Forutsetninger!$B$5*Forutsetninger!$B$41*Forutsetninger!$B$31 | Z82: =SUM(B82:M82) | AA82: =SUM(N82:Y82)
A83: (memo) Netto mva påløpt (utg. på salg − inng. på kost) | B83: =$B$35*B68-$B$35*(B82+$B$36*B80) | C83: =$B$35*C68-$B$35*(C82+$B$36*C80) | D83: =$B$35*D68-$B$35*(D82+$B$36*D80) | E83: =$B$35*E68-$B$35*(E82+$B$36*E80) | F83: =$B$35*F68-$B$35*(F82+$B$36*F80) | G83: =$B$35*G68-$B$35*(G82+$B$36*G80) | H83: =$B$35*H68-$B$35*(H82+$B$36*H80) | I83: =$B$35*I68-$B$35*(I82+$B$36*I80) | ... Y83: =$B$35*Y68-$B$35*(Y82+$B$36*Y80) | Z83: =SUM(B83:M83) | AA83: =SUM(N83:Y83)
A84: Mva-oppgjør (annenhver måned) | B84: 0 | C84: 0 | D84: 0 | E84: =B83+C83 | F84: 0 | G84: =D83+E83 | H84: 0 | I84: =F83+G83 | J84: 0 | K84: =H83+I83 | L84: 0 | M84: =J83+K83 | N84: 0 | O84: =L83+M83 | P84: 0 | Q84: =N83+O83 | R84: 0 | S84: =P83+Q83 | T84: 0 | U84: =R83+S83 | V84: 0 | W84: =T83+U83 | X84: 0 | Y84: =V83+W83 | Z84: =SUM(B84:M84) | AA84: =SUM(N84:Y84)
A85: Restskatt 2026 (betales 15/2 + 15/4 2027) | B85: 0 | C85: PLASSHOLDER. Skatt 2025 (179k) er betalt. Forskuddsskatt 2026 forfaller feb+apr 2027.
A86: Resultat-proxy 2027 (ex mva, for skatt 2028) | Z86: =Z68-Z78-Z79-Z82-Z80
A87: Selskapsskatt 2027 (22 % av positivt resultat) | B87: =0.22*MAX(0,Z86)
A88: Selskapsskatt (forskudd feb/apr) | B88: 0 | C88: =$B$85/2 | D88: 0 | E88: =$B$85/2 | F88: 0 | G88: 0 | H88: 0 | I88: 0 | J88: 0 | K88: 0 | L88: 0 | M88: 0 | N88: 0 | O88: =$B$87/2 | P88: 0 | Q88: =$B$87/2 | R88: 0 | S88: 0 | T88: 0 | U88: 0 | V88: 0 | W88: 0 | X88: 0 | Y88: 0 | Z88: =SUM(B88:M88) | AA88: =SUM(N88:Y88)
A89: Kjente engangsposter — beløp (GUL) og måned 1–24 (GUL)
A90: Besluttet utbytte (rest) | B90: 850000 | C90: 9 | D90: 850k besluttet, 0 utbetalt (Sindre 28.08). Timing valgfri — H2-oppgjør anbefalt. Mnd 9 = sep 2027.
A91: Motfakturering Oslo Båt / krympeplast (netto) | B91: 125000 | C91: 11 | D91: Sindre: ~100–150k motfaktureres. Netto anslag 125k. Juster.
A92: Underleverandør | B92: 50000 | C92: 10 | D92: Sindre: ~50k.
A93: (ledig)
A94: (ledig)
A95: Sum engangsposter | B95: =SUMPRODUCT(($C$90:$C$94=1)*N($B$90:$B$94)) | C95: =SUMPRODUCT(($C$90:$C$94=2)*N($B$90:$B$94)) | D95: =SUMPRODUCT(($C$90:$C$94=3)*N($B$90:$B$94)) | E95: =SUMPRODUCT(($C$90:$C$94=4)*N($B$90:$B$94)) | F95: =SUMPRODUCT(($C$90:$C$94=5)*N($B$90:$B$94)) | G95: =SUMPRODUCT(($C$90:$C$94=6)*N($B$90:$B$94)) | H95: =SUMPRODUCT(($C$90:$C$94=7)*N($B$90:$B$94)) | I95: =SUMPRODUCT(($C$90:$C$94=8)*N($B$90:$B$94)) | J95: =SUMPRODUCT(($C$90:$C$94=9)*N($B$90:$B$94)) | K95: =SUMPRODUCT(($C$90:$C$94=10)*N($B$90:$B$94)) | L95: =SUMPRODUCT(($C$90:$C$94=11)*N($B$90:$B$94)) | M95: =SUMPRODUCT(($C$90:$C$94=12)*N($B$90:$B$94)) | N95: =SUMPRODUCT(($C$90:$C$94=13)*N($B$90:$B$94)) | O95: =SUMPRODUCT(($C$90:$C$94=14)*N($B$90:$B$94)) | P95: =SUMPRODUCT(($C$90:$C$94=15)*N($B$90:$B$94)) | Q95: =SUMPRODUCT(($C$90:$C$94=16)*N($B$90:$B$94)) | R95: =SUMPRODUCT(($C$90:$C$94=17)*N($B$90:$B$94)) | S95: =SUMPRODUCT(($C$90:$C$94=18)*N($B$90:$B$94)) | T95: =SUMPRODUCT(($C$90:$C$94=19)*N($B$90:$B$94)) | U95: =SUMPRODUCT(($C$90:$C$94=20)*N($B$90:$B$94)) | V95: =SUMPRODUCT(($C$90:$C$94=21)*N($B$90:$B$94)) | W95: =SUMPRODUCT(($C$90:$C$94=22)*N($B$90:$B$94)) | X95: =SUMPRODUCT(($C$90:$C$94=23)*N($B$90:$B$94)) | Y95: =SUMPRODUCT(($C$90:$C$94=24)*N($B$90:$B$94)) | Z95: =SUM(B95:M95) | AA95: =SUM(N95:Y95)
A97: H. NETTO KONTANTSTRØM OG SALDO
A98: SUM INNBETALINGER | B98: =B74 | C98: =C74 | D98: =D74 | E98: =E74 | F98: =F74 | G98: =G74 | H98: =H74 | I98: =I74 | ... Y98: =Y74 | Z98: =SUM(B98:M98) | AA98: =SUM(N98:Y98)
A99: SUM UTBETALINGER | B99: =B78+B79+B80+B81+B82+B84+B88+B95 | C99: =C78+C79+C80+C81+C82+C84+C88+C95 | D99: =D78+D79+D80+D81+D82+D84+D88+D95 | E99: =E78+E79+E80+E81+E82+E84+E88+E95 | F99: =F78+F79+F80+F81+F82+F84+F88+F95 | G99: =G78+G79+G80+G81+G82+G84+G88+G95 | H99: =H78+H79+H80+H81+H82+H84+H88+H95 | I99: =I78+I79+I80+I81+I82+I84+I88+I95 | ... Y99: =Y78+Y79+Y80+Y81+Y82+Y84+Y88+Y95 | Z99: =SUM(B99:M99) | AA99: =SUM(N99:Y99)
A100: NETTO KONTANTSTRØM | B100: =B98-B99 | C100: =C98-C99 | D100: =D98-D99 | E100: =E98-E99 | F100: =F98-F99 | G100: =G98-G99 | H100: =H98-H99 | I100: =I98-I99 | ... Y100: =Y98-Y99 | Z100: =SUM(B100:M100) | AA100: =SUM(N100:Y100)
A101: Inngående saldo | B101: =$B$28 | C101: =B102 | D101: =C102 | E101: =D102 | F101: =E102 | G101: =F102 | H101: =G102 | I101: =H102 | J101: =I102 | ... Y101: =X102
A102: UTGÅENDE SALDO (kontantbeholdning) | B102: =B101+B100 | C102: =C101+C100 | D102: =D101+D100 | E102: =E101+E100 | F102: =F101+F100 | G102: =G101+G100 | H102: =H101+H100 | I102: =I101+I100 | ... Y102: =Y101+Y100 | AA102: =Y102
A103: Margin mot minimumsbuffer | B103: =B102-$B$29 | C103: =C102-$B$29 | D103: =D102-$B$29 | E103: =E102-$B$29 | F103: =F102-$B$29 | G103: =G102-$B$29 | H103: =H102-$B$29 | I103: =I102-$B$29 | ... Y103: =Y102-$B$29
A105: Kontroll: UB des 2028 − (åpning + sum netto) | B105: =Y102-($B$28+SUM(B100:Y100)) | C105: skal være 0
A107: SLIK LESER DU ARKET
A108: Motoren er den samme som ellers i boka: bemanning (D) → kapasitet → omsetning bokført (E). Det nye er TIMING — når pengene faktisk kommer inn (F) og går ut (G), måned for måned.
A109: LAVESTE KONTANTSALDO (øverst) er poenget: det dypeste punktet på UTGÅENDE SALDO-raden. Faller den under bufferen, lyser margin-raden negativt — da trengs tiltak FØR den måneden (tregere ansettelse, utsatt utbytte, kassekreditt).
A110: CASH-LAG: provisjonen tas ved OPPGJØR (senest 3 dg etter overtakelse). Fakturadato brukes som operativ cash-proxy (median 14d fra salg). Konservativt: bruk Plan (P75, 32d). Salgstid 89 dg (signert→solgt) er noe HELT ANNET — ikke bland dem.
A111: PRØV SPAKENE: cash-lag scenario 1/2/3 (Base/Plan/Stress); flytt utbyttemåneden; utsett en ansettelse (endre oppstartsmåned i D). Alt regner seg om.
...

Sheet Forutsetninger
A1: FORUTSETNINGER — én datadefinisjon per KPI
A2: Gule celler = juster fritt (alt rekalkulerer). FASIT = oppgjørslistene («lønn solgte båter»), ikke HubSpot. Oppdatert 26.08.2026.
A4: FASIT SALG — kilde: oppgjørslister 2025+2026, solgt-dato 27.08.2025–26.08.2026, EX CHARTER
A5: Inntekt per solgt båt, ex mva (MOTOR-INPUT) | B5: 58375 | C5: DEF: sum omsetning ex mva 4 378 153 / 75 båtsalg i oppgjørslistene siste 12 mnd. Median 50 400. Alle 75 har beløp (fasit — ikke HubSpot-amount, som manglet 4 deals og ga 64 100). Charter (170k) holdt HELT utenfor.
A6: Snittbåtverdi (salgssum) — informativ | B6: 1260458 | C6: DEF: snitt salgssum i oppgjørslistene, 75/75 deals. Median 1 065 000. Brukes IKKE i motoren.
A7: Provisjonsgrad 1: standard avtalt | B7: 0.06 | C7: DEF: 6,00 % av salgssum INKL mva, min. 45 000 inkl mva (= 36 000 ex). Kontraktsstandard.
A8: Provisjonsgrad 2: målt effektiv (fasit, alle 75) | B8: 0.0579 | C8: DEF: sum(oms ex mva × 1,25) / sum(salgssum) = 5,79 % inkl mva (4,63 % ex). Teller og nevner er nå SAMME utvalg (75/75) — kontrolltallet fra v2 er dermed identisk og trengs ikke lenger. Gap til 6 % = rabatter/min.honorar.
A9: Charter — holdes utenfor motoren | B9: 170000 | C9: 1 charteroppdrag siste 12 mnd (AD Astra, 170 000 ex mva). Egen produksjonsenhet; regnes IKKE i inntekt per båt, båter/år eller stol-kapasitet.
A11: STOL-DEFINISJONER OG KAPASITET
A12: DEF «stol» | C12: Én fullt produktiv megler ETTER ramp (6–9 mnd). Sindre er ALLTID egen stol utenom. «Producing FTE» = effektiv produksjonskapasitet i året (ramp-vektet, desimal). «Bemannet» = personer på lønn. Buffer-stol = planlagt tom (rekrutteringspipeline).
A13: Omsetning per producing megler-stol (plantall) | B13: 1500000 | C13: PRODUKSJONSMÅL for rampet stol. Fasit siste 12 mnd KREDITERT (50/50 v/samarbeid — det lønna følger): Henrik 1 838 820, Sindre 1 491 253, Daniel 882 480. Solgt av: Henrik 2 007 420 (35 båter) — han lukker også andres oppdrag.
A14: Sindre-stolens omsetning per år (plantall) | B14: 2300000 | C14: CFO-anbefalt mål ~2,28M. Fasit siste 12 mnd kreditert: 1 491 253 (2025: 2 083 205) — inkl. lederrolle; han HENTET oppdrag for langt mer (2,5M inn i 2025).
A15: Break-even per ny stol (egne kostnader) | B15: =$B$26/(1-$B$34-$B$31*$B$41/$B$5) | C15: FORMEL: løpende trinnkost ÷ megler-marginal (1−0,55−markedskost-rate) ≈ 200k omsetning dekker stolens EGNE kostnader. Å dekke en ANDEL av felles faste krever ~1,2–1,7M (jf. «Lønnsomhet per megler» i kostnadsmodellen) — det er Sindres poeng om når en megler begynner å tjene penger.
A16: Churn-buffer (stoler planlagt tomme) | B16: 1 | C16: Ditt valg: planlegg alltid som om én stol står tom (Daniel-effekten).
A17: Megler-stoler bemannet i dag (utenom Sindre) | B17: 1 | C17: Henrik (+Marte som assistent). Daniel slutter → telles ikke.
A19: RAMP-PROFIL FOR NYANSATT MEGLER (PLANANTAKELSE)
A20: Produksjon måned 1–3 (andel av full stol) | B20: 0.4 | C20: EMPIRI (begge startet mars/apr 2025): Henrik solgte 1 963k i år 1 (2,35M-rate), Daniel 570k (0,76M-rate) — snitt ≈ full stol, men enorm spredning. 40/75/100 ligger bevisst under snittet av n=2.
A21: Produksjon måned 4–6 | B21: 0.75 | C21: Egen portefølje bygges. Median salgstid 89 dg → første oppgjør kommer ~3 mnd etter første oppdrag.
A22: Produksjon måned 7–12 | B22: 1 | C22: Fullt producing fra ~mnd 7. Henrik beviste at det er mulig; churn-bufferen tar høyde for en Daniel-profil.
A24: TRINNVIS KOSTBASE (PLANANTAKELSE — juster mot egne tall)
A25: Grunnkostbase per år (dekker inntil 2 megler-stoler) | B25: 1880000 | C25: DEF: kostbase fullastet 2,54M (kostnadsmodell jun 2026) minus markedskost-andelen. Inkl. Marte, Philip, avskrivning 228k, kontor, systemer — dagens nivå.
A26: Løpende tilleggskost per bemannet stol utover 2 | B26: 60000 | C26: FASIT-BASERT (kostnadsbudsjett 2026): parkering ~18k + CRM/lisenser ~30k + telefon/forsikring ~12k per hode. Kontor koster INGENTING før stol nr. 6 (plass på dagens kontor).
A27: Engangs rekrutterings-/onboardingkost per nyansettelse | B27: 75000 | C27: PLANANTAKELSE: annonsering, intervjutid, utstyr, opplæring — belastes ansettelsesåret.
A28: Kontorutvidelse fra ≥6 bemannede stoler | B28: 300000 | C28: PLASSHOLDER — dagens kontor har plass til ~5. Sjekk leieavtalen for faktisk kostnad ved utvidelse.
A29: Salgsleder/daglig-leder-kapasitet fra ≥5 stoler | B29: 900000 | C29: PLANANTAKELSE: ved 5+ meglere kan ikke Sindre både selge 2,3M og lede alene.
A30: Ekstra backoffice/administrasjon fra ≥8 stoler | B30: 500000 | C30: PLANANTAKELSE: kundeservice, oppgjør, kontor.
A31: Markedskost per signert oppdrag inn | B31: 6600 | C31: DEF: målt snitt per SIGNERT oppdrag. CFO-mål: 4 552 + 15k-tak håndheves.
A33: MEGLERKOST OG SINDRE-LØNN
A34: Meglerkost, fullastet andel av megler-omsetning | B34: 0.55 | C34: DEF: meglerprovisjon (40 %) + AGA + feriepenger ≈ 55 øre per megler-omsetningskrone.
A35: Grunnbeløpet G (per 1.5.2026) | B35: 136549 | C35: Kilde: nav.no/grunnbelopet. Oppdateres hver mai.
A36: Sindres lønnstak (7,1G) | B36: =7.1*$B$35 | C36: DEF: 7,1G = taket for pensjonsopptjening i folketrygden — over dette lønner utbytte seg. Pensjonsgivende inntekt inkluderer feriepenger.
A37: Sindres provisjonssats | B37: 0.45 | C37: 45 % av egen omsetning ex mva (før tak).
A38: Lønns-loading (AGA + feriepenger) | B38: 1.165 | C38: For Sindre: AGA/OTP-påslag. 7,1G-taket antas å INKLUDERE feriepenger (12 %, ikke 10,2) → grunnlønn ≈ 865 623 + 12 % FP = 969 498. MARIUS BEKREFTER inkl/eks-tolkningen; eks-tolkning koster ~115k mer.
A40: TRAKT — kilder: kohortanalyse (Historikk) + HubSpot Pipeline A per 26.08.2026
A41: Signerte oppdrag inn per solgt båt (PLANANTAKELSE) | B41: 1.3 | C41: KOHORTMÅLT på modne oppdrag (>365 dg, n=58): 72 % solgt → 58/42 = 1,38 oppdrag/salg; hvis alle 8 åpne til slutt selges: 58/50 = 1,16. 1,30 = planantakelse mellom. v2-tallet 1,15 forkastet (samtidighetsfeil, jf. rådgiver).
A42: Vinnrate Pipeline A — PROXY for befaring→signering | B42: 0.68 | C42: PROXY, IKKE målt close rate befaring→signering! DEF: 67 vunnet / 99 avgjorte deals i Pipeline A siste 12 mnd (hele trakten, prospect→signert). Isolert befaring→signering krever stage-historikk — mangler (mål: 90 %).
A43: Prospect → befaring-rate (plantall) | B43: 0.5 | C43: Målt per megler (CFO-analyse): Sindre 74 %, Daniel 52 %, Henrik+Marte 28 %.
A44: Arbeidsuker per år | B44: 46 | C44: Ferie/helligdager trukket fra.
A46: SCORECARD-PARAMETRE (H2 2026)
A47: H2-2026-mål omsetning ex mva (uten Daniel) | B47: 2900000 | C47: Fra revidert H2-plan aug 2026.
A48: H2 levert hittil ex mva (fasit, per 26.08) | B48: 626060 | C48: Oppgjørsliste 2026: juli 392 960 + august 233 100. Oppdater ukentlig.
A49: Hele uker igjen av H2 2026 | B49: 17 | C49: ISO-uke 36–52 = 17 hele uker (i dag er uke 35 — inneværende deluke telles IKKE). Reduser med 1 hver mandag.
A51: MANGLER – MÅ MÅLES
A52: Befaring → signering isolert (mål 90 %) | C52: Krever stage-historikk i Pipeline A — sett opp HubSpot-rapport. Største traktehull.
A53: Presise signerings-/salgsdatoer til kohorten | C53: B-deal createdate er proxy for signeringsdato; closedate delvis bulk-satt. Supabase oppdrag_livslop (433 rader) kan gi presise datoer.
A54: Henvendelse → befaring per kilde | C54: FINN / nettside / referral / FSBO. Lead source må fylles konsekvent.
A55: FSBO-/outreach-aktivitet per megler per uke | C55: Logges ikke i dag — inn i scorecardet.
A56: Faktiske trinnkostnader ved vekst | C56: 150k/stol, 900k leder, 500k backoffice er PLANANTAKELSER — kalibrer mot tilbud/regnskap før 3/5-års bemanning låses.

Sheet Weekly Scorecard
A1: WEEKLY SCORECARD — koblet til motoren (fyll inn hver fredag)
A2: STYR PÅ ÉN LINJE: provisjon ex mva (hovedmålet). Leading-kolonnene forklarer NESTE måneds provisjon (salgstid ~89 dg). «H2-rest» = (mål − levert)/uker igjen — oppdater ukentlig.
A3: Befaring-målet bruker 68 % PROXY-vinnrate. Rekrutteringsstatus er fast punkt i ukemøtet.
A5: Uke | B5: Nye prospects | C5: Befaringer | D5: Signerte oppdrag | E5: Båter solgt | F5: Provisjon ex mva | G5: Publisert ≤7 dg | H5: Actions neste uke | I5: R/G/G
A6: Type | B6: LEADING | C6: LEADING | D6: LEADING | E6: LAGGING | F6: ★ HOVEDMÅL | G6: KONTROLL
A7: MÅL: H2-rest (per KALENDERUKE, 17 igjen) | B7: =((Forutsetninger!$B$47-Forutsetninger!$B$48)/Forutsetninger!$B$5/Forutsetninger!$B$49)*Forutsetninger!$B$41/Forutsetninger!$B$42/Forutsetninger!$B$43 | C7: =((Forutsetninger!$B$47-Forutsetninger!$B$48)/Forutsetninger!$B$5/Forutsetninger!$B$49)*Forutsetninger!$B$41/Forutsetninger!$B$42 | D7: =((Forutsetninger!$B$47-Forutsetninger!$B$48)/Forutsetninger!$B$5/Forutsetninger!$B$49)*Forutsetninger!$B$41 | E7: =((Forutsetninger!$B$47-Forutsetninger!$B$48)/Forutsetninger!$B$5/Forutsetninger!$B$49) | F7: =(Forutsetninger!$B$47-Forutsetninger!$B$48)/Forutsetninger!$B$49 | G7: 1
A8: Info: År 1-behov 2027 (per ARBEIDSUKE av 46 — IKKE sammenlignbar med H2-linjen) | B8: ='1-3-5 Plan'!C30 | C8: ='1-3-5 Plan'!C28 | D8: ='1-3-5 Plan'!C26 | E8: ='1-3-5 Plan'!C14/Forutsetninger!$B$44 | F8: ='1-3-5 Plan'!C8/Forutsetninger!$B$44 | G8: 1
A10: 36
A11: 37
A12: 38
A13: 39
A14: 40
A15: 41
A16: 42
A17: 43
A18: 44
A19: 45
A20: 46
A21: 47
... A30: Definisjoner: Nye prospects = deals opprettet i Pipeline A. Befaringer = holdte. Signerte = Vunnet i A. Provisjon = oppgjørsliste ex mva.
